conditional/systemx.vhd
library IEEE;
use ieee.std_logic_1164.all; -- contains std_logic data types
use IEEE.numeric_std.all; -- contains function like "to_unsigned"

entity systemx is
    port (A, B, C : in std_logic;
        F : out std_logic);
end entity;

architecture systemx_arch of systemx is

    begin
        -- trigger process is assigned
        cmb1 : process (A, B, C) is

            -- define variable here
            variable ABC : std_logic_vector(2 downto 0) := "000";

            begin
                case (ABC) is
                    when "010" => F <= '1';
                    when "101" => F <= '1';
                    when "110" => F <= '1';
                    when others => F <= '0';
                end case;


        end process;

end architecture; -- systemx_arch

conditional/systemx_tb.vhd
library IEEE;
use ieee.std_logic_1164.all; -- contains std_logic data types
use IEEE.numeric_std.all; -- contains function like "to_unsigned"

entity systemx_tb is
    -- empty for testbenches
end entity;

architecture systemx_arch_tb of systemx_tb is
    component systemx is
        port (A, B, C : in std_logic;
            F : out std_logic);
    end component;

    signal signal_a, signal_b, signal_c, signal_f : std_logic;
    constant n : integer:= 3;

    begin
        comp : systemx port map (
            A => signal_a,
            B => signal_b,
            C => signal_c,
            F => signal_f
        );
    process
        variable i : integer;
        begin
            for i in 0 to 7 loop
                (signal_a,signal_b,signal_c) <= std_logic_vector(to_unsigned(i, n));
                report "signal_a: " & std_logic'image(signal_a);
                report "signal_b: " & std_logic'image(signal_b);
                report "signal_c: " & std_logic'image(signal_c);
                wait for 1 ns;
                report "nothing";
                report "signal_f: " & std_logic'image(signal_f);
            end loop;
    end process;

end architecture;

conditional/systemx.vcd
$date
  Wed Apr  6 06:01:10 2022
$end
$version
  GHDL v0
$end
$timescale
  1 fs
$end
$scope module standard $end
$upscope $end
$scope module textio $end
$upscope $end
$scope module std_logic_1164 $end
$upscope $end
$scope module numeric_std $end
$upscope $end
$scope module systemx_tb $end
$var reg 1 ! signal_a $end
$var reg 1 " signal_b $end
$var reg 1 # signal_c $end
$var reg 1 $ signal_f $end
$scope module comp $end
$var reg 1 % a $end
$var reg 1 & b $end
$var reg 1 ' c $end
$var reg 1 ( f $end
$upscope $end
$upscope $end
$enddefinitions $end
#0
0!
0"
0#
0$
0%
0&
0'
0(
#1000000
1#
1'
#2000000
1"
0#
1&
0'
#3000000
1#
1'
#4000000
1!
0"
0#
1%
0&
0'
#5000000
1#
1'
#6000000
1"
0#
1&
0'
#7000000
1#
1'
#8000000
0!
0"
0#
0%
0&
0'
#9000000
1#
1'
#10000000
1"
0#
1&
0'
#11000000
1#
1'
#12000000
1!
0"
0#
1%
0&
0'
#13000000
1#
1'
#14000000
1"
0#
1&
0'
#15000000
1#
1'
#16000000
0!
0"
0#
0%
0&
0'
#17000000
1#
1'
#18000000
1"
0#
1&
0'
#19000000
1#
1'
#20000000
1!
0"
0#
1%
0&
0'
#21000000
1#
1'
#22000000
1"
0#
1&
0'
#23000000
1#
1'
#24000000
0!
0"
0#
0%
0&
0'
#25000000
1#
1'
#26000000
1"
0#
1&
0'
#27000000
1#
1'
#28000000
1!
0"
0#
1%
0&
0'
#29000000
1#
1'
#30000000
1"
0#
1&
0'
#31000000
1#
1'
#32000000
0!
0"
0#
0%
0&
0'
#33000000
1#
1'
#34000000
1"
0#
1&
0'
#35000000
1#
1'
#36000000
1!
0"
0#
1%
0&
0'
#37000000
1#
1'
#38000000
1"
0#
1&
0'
#39000000
1#
1'
#40000000
0!
0"
0#
0%
0&
0'
#41000000
1#
1'
#42000000
1"
0#
1&
0'
#43000000
1#
1'
#44000000
1!
0"
0#
1%
0&
0'
#45000000
1#
1'
#46000000
1"
0#
1&
0'
#47000000
1#
1'
#48000000
0!
0"
0#
0%
0&
0'
#49000000
1#
1'
#50000000
1"
0#
1&
0'
#51000000
1#
1'
#52000000
1!
0"
0#
1%
0&
0'
#53000000
1#
1'
#54000000
1"
0#
1&
0'
#55000000
1#
1'
#56000000
0!
0"
0#
0%
0&
0'
#57000000
1#
1'
#58000000
1"
0#
1&
0'
#59000000
1#
1'
#60000000
1!
0"
0#
1%
0&
0'
#61000000
1#
1'
#62000000
1"
0#
1&
0'
#63000000
1#
1'
#64000000
0!
0"
0#
0%
0&
0'
#65000000
1#
1'
#66000000
1"
0#
1&
0'
#67000000
1#
1'
#68000000
1!
0"
0#
1%
0&
0'
#69000000
1#
1'
#70000000
1"
0#
1&
0'
#71000000
1#
1'
#72000000
0!
0"
0#
0%
0&
0'
#73000000
1#
1'
#74000000
1"
0#
1&
0'
#75000000
1#
1'
#76000000
1!
0"
0#
1%
0&
0'
#77000000
1#
1'
#78000000
1"
0#
1&
0'
#79000000
1#
1'
#80000000
0!
0"
0#
0%
0&
0'
#81000000
1#
1'
#82000000
1"
0#
1&
0'
#83000000
1#
1'
#84000000
1!
0"
0#
1%
0&
0'
#85000000
1#
1'
#86000000
1"
0#
1&
0'
#87000000
1#
1'
#88000000
0!
0"
0#
0%
0&
0'
#89000000
1#
1'
#90000000
1"
0#
1&
0'
#91000000
1#
1'
#92000000
1!
0"
0#
1%
0&
0'
#93000000
1#
1'
#94000000
1"
0#
1&
0'
#95000000
1#
1'
#96000000
0!
0"
0#
0%
0&
0'
#97000000
1#
1'
#98000000
1"
0#
1&
0'
#99000000
1#
1'
#100000000
1!
0"
0#
1%
0&
0'
#101000000
1#
1'
#102000000
1"
0#
1&
0'
#103000000
1#
1'
#104000000
0!
0"
0#
0%
0&
0'
#105000000
1#
1'
#106000000
1"
0#
1&
0'
#107000000
1#
1'
#108000000
1!
0"
0#
1%
0&
0'
#109000000
1#
1'
#110000000
1"
0#
1&
0'
#111000000
1#
1'
#112000000
0!
0"
0#
0%
0&
0'
#113000000
1#
1'
#114000000
1"
0#
1&
0'
#115000000
1#
1'
#116000000
1!
0"
0#
1%
0&
0'
#117000000
1#
1'
#118000000
1"
0#
1&
0'
#119000000
1#
1'
#120000000
0!
0"
0#
0%
0&
0'
#121000000
1#
1'
#122000000
1"
0#
1&
0'
#123000000
1#
1'
#124000000
1!
0"
0#
1%
0&
0'
#125000000
1#
1'
#126000000
1"
0#
1&
0'
#127000000
1#
1'
#128000000
0!
0"
0#
0%
0&
0'
#129000000
1#
1'
#130000000
1"
0#
1&
0'
#131000000
1#
1'
#132000000
1!
0"
0#
1%
0&
0'
#133000000
1#
1'
#134000000
1"
0#
1&
0'
#135000000
1#
1'
#136000000
0!
0"
0#
0%
0&
0'
#137000000
1#
1'
#138000000
1"
0#
1&
0'
#139000000
1#
1'
#140000000
1!
0"
0#
1%
0&
0'
#141000000
1#
1'
#142000000
1"
0#
1&
0'
#143000000
1#
1'
#144000000
0!
0"
0#
0%
0&
0'
#145000000
1#
1'
#146000000
1"
0#
1&
0'
#147000000
1#
1'
#148000000
1!
0"
0#
1%
0&
0'
#149000000
1#
1'
#150000000
1"
0#
1&
0'
#151000000
1#
1'
#152000000
0!
0"
0#
0%
0&
0'
#153000000
1#
1'
#154000000
1"
0#
1&
0'
#155000000
1#
1'
#156000000
1!
0"
0#
1%
0&
0'
#157000000
1#
1'
#158000000
1"
0#
1&
0'
#159000000
1#
1'
#160000000
0!
0"
0#
0%
0&
0'
#161000000
1#
1'
#162000000
1"
0#
1&
0'
#163000000
1#
1'
#164000000
1!
0"
0#
1%
0&
0'
#165000000
1#
1'
#166000000
1"
0#
1&
0'
#167000000
1#
1'
#168000000
0!
0"
0#
0%
0&
0'
#169000000
1#
1'
#170000000
1"
0#
1&
0'
#171000000
1#
1'
#172000000
1!
0"
0#
1%
0&
0'
#173000000
1#
1'
#174000000
1"
0#
1&
0'
#175000000
1#
1'
#176000000
0!
0"
0#
0%
0&
0'
#177000000
1#
1'
#178000000
1"
0#
1&
0'
#179000000
1#
1'
#180000000
1!
0"
0#
1%
0&
0'
#181000000
1#
1'
#182000000
1"
0#
1&
0'
#183000000
1#
1'
#184000000
0!
0"
0#
0%
0&
0'
#185000000
1#
1'
#186000000
1"
0#
1&
0'
#187000000
1#
1'
#188000000
1!
0"
0#
1%
0&
0'
#189000000
1#
1'
#190000000
1"
0#
1&
0'
#191000000
1#
1'
#192000000
0!
0"
0#
0%
0&
0'
#193000000
1#
1'
#194000000
1"
0#
1&
0'
#195000000
1#
1'
#196000000
1!
0"
0#
1%
0&
0'
#197000000
1#
1'
#198000000
1"
0#
1&
0'
#199000000
1#
1'
#200000000
0!
0"
0#
0%
0&
0'
#201000000
1#
1'
#202000000
1"
0#
1&
0'
#203000000
1#
1'
#204000000
1!
0"
0#
1%
0&
0'
#205000000
1#
1'
#206000000
1"
0#
1&
0'
#207000000
1#
1'
#208000000
0!
0"
0#
0%
0&
0'
#209000000
1#
1'
#210000000
1"
0#
1&
0'
#211000000
1#
1'
#212000000
1!
0"
0#
1%
0&
0'
#213000000
1#
1'
#214000000
1"
0#
1&
0'
#215000000
1#
1'
#216000000
0!
0"
0#
0%
0&
0'
#217000000
1#
1'
#218000000
1"
0#
1&
0'
#219000000
1#
1'
#220000000
1!
0"
0#
1%
0&
0'
#221000000
1#
1'
#222000000
1"
0#
1&
0'
#223000000
1#
1'
#224000000
0!
0"
0#
0%
0&
0'
#225000000
1#
1'
#226000000
1"
0#
1&
0'
#227000000
1#
1'
#228000000
1!
0"
0#
1%
0&
0'
#229000000
1#
1'
#230000000
1"
0#
1&
0'
#231000000
1#
1'
#232000000
0!
0"
0#
0%
0&
0'
#233000000
1#
1'
#234000000
1"
0#
1&
0'
#235000000
1#
1'
#236000000
1!
0"
0#
1%
0&
0'
#237000000
1#
1'
#238000000
1"
0#
1&
0'
#239000000
1#
1'
#240000000
0!
0"
0#
0%
0&
0'
#241000000
1#
1'
#242000000
1"
0#
1&
0'
#243000000
1#
1'
#244000000
1!
0"
0#
1%
0&
0'
#245000000
1#
1'
#246000000
1"
0#
1&
0'
#247000000
1#
1'
#248000000
0!
0"
0#
0%
0&
0'
#249000000
1#
1'
#250000000
1"
0#
1&
0'
#251000000
1#
1'
#252000000
1!
0"
0#
1%
0&
0'
#253000000
1#
1'
#254000000
1"
0#
1&
0'
#255000000
1#
1'
#256000000
0!
0"
0#
0%
0&
0'
#257000000
1#
1'
#258000000
1"
0#
1&
0'
#259000000
1#
1'
#260000000
1!
0"
0#
1%
0&
0'
#261000000
1#
1'
#262000000
1"
0#
1&
0'
#263000000
1#
1'
#264000000
0!
0"
0#
0%
0&
0'
#265000000
1#
1'
#266000000
1"
0#
1&
0'
#267000000
1#
1'
#268000000
1!
0"
0#
1%
0&
0'
#269000000
1#
1'
#270000000
1"
0#
1&
0'
#271000000
1#
1'
#272000000
0!
0"
0#
0%
0&
0'
#273000000
1#
1'
#274000000
1"
0#
1&
0'
#275000000
1#
1'
#276000000
1!
0"
0#
1%
0&
0'
#277000000
1#
1'
#278000000
1"
0#
1&
0'
#279000000
1#
1'
#280000000
0!
0"
0#
0%
0&
0'
#281000000
1#
1'
#282000000
1"
0#
1&
0'
#283000000
1#
1'
#284000000
1!
0"
0#
1%
0&
0'
#285000000
1#
1'
#286000000
1"
0#
1&
0'
#287000000
1#
1'
#288000000
0!
0"
0#
0%
0&
0'
#289000000
1#
1'
#290000000
1"
0#
1&
0'
#291000000
1#
1'
#292000000
1!
0"
0#
1%
0&
0'
#293000000
1#
1'
#294000000
1"
0#
1&
0'
#295000000
1#
1'
#296000000
0!
0"
0#
0%
0&
0'
#297000000
1#
1'
#298000000
1"
0#
1&
0'
#299000000
1#
1'
#300000000
1!
0"
0#
1%
0&
0'
#301000000
1#
1'
#302000000
1"
0#
1&
0'
#303000000
1#
1'
#304000000
0!
0"
0#
0%
0&
0'
#305000000
1#
1'
#306000000
1"
0#
1&
0'
#307000000
1#
1'
#308000000
1!
0"
0#
1%
0&
0'
#309000000
1#
1'
#310000000
1"
0#
1&
0'
#311000000
1#
1'
#312000000
0!
0"
0#
0%
0&
0'
#313000000
1#
1'
#314000000
1"
0#
1&
0'
#315000000
1#
1'
#316000000
1!
0"
0#
1%
0&
0'
#317000000
1#
1'
#318000000
1"
0#
1&
0'
#319000000
1#
1'
#320000000
0!
0"
0#
0%
0&
0'
#321000000
1#
1'
#322000000
1"
0#
1&
0'
#323000000
1#
1'
#324000000
1!
0"
0#
1%
0&
0'
#325000000
1#
1'
#326000000
1"
0#
1&
0'
#327000000
1#
1'
#328000000
0!
0"
0#
0%
0&
0'
#329000000
1#
1'
#330000000
1"
0#
1&
0'
#331000000
1#
1'
#332000000
1!
0"
0#
1%
0&
0'
#333000000
1#
1'
#334000000
1"
0#
1&
0'
#335000000
1#
1'
#336000000
0!
0"
0#
0%
0&
0'
#337000000
1#
1'
#338000000
1"
0#
1&
0'
#339000000
1#
1'
#340000000
1!
0"
0#
1%
0&
0'
#341000000
1#
1'
#342000000
1"
0#
1&
0'
#343000000
1#
1'
#344000000
0!
0"
0#
0%
0&
0'
#345000000
1#
1'
#346000000
1"
0#
1&
0'
#347000000
1#
1'
#348000000
1!
0"
0#
1%
0&
0'
#349000000
1#
1'
#350000000
1"
0#
1&
0'
#351000000
1#
1'
#352000000
0!
0"
0#
0%
0&
0'
#353000000
1#
1'
#354000000
1"
0#
1&
0'
#355000000
1#
1'
#356000000
1!
0"
0#
1%
0&
0'
#357000000
1#
1'
#358000000
1"
0#
1&
0'
#359000000
1#
1'
#360000000
0!
0"
0#
0%
0&
0'
#361000000
1#
1'
#362000000
1"
0#
1&
0'
#363000000
1#
1'
#364000000
1!
0"
0#
1%
0&
0'
#365000000
1#
1'
#366000000
1"
0#
1&
0'
#367000000
1#
1'
#368000000
0!
0"
0#
0%
0&
0'
#369000000
1#
1'
#370000000
1"
0#
1&
0'
#371000000
1#
1'
#372000000
1!
0"
0#
1%
0&
0'
#373000000
1#
1'
#374000000
1"
0#
1&
0'
#375000000
1#
1'
#376000000
0!
0"
0#
0%
0&
0'
#377000000
1#
1'
#378000000
1"
0#
1&
0'
#379000000
1#
1'
#380000000
1!
0"
0#
1%
0&
0'
#381000000
1#
1'
#382000000
1"
0#
1&
0'
#383000000
1#
1'
#384000000
0!
0"
0#
0%
0&
0'
#385000000
1#
1'
#386000000
1"
0#
1&
0'
#387000000
1#
1'
#388000000
1!
0"
0#
1%
0&
0'
#389000000
1#
1'
#390000000
1"
0#
1&
0'
#391000000
1#
1'
#392000000
0!
0"
0#
0%
0&
0'
#393000000
1#
1'
#394000000
1"
0#
1&
0'
#395000000
1#
1'
#396000000
1!
0"
0#
1%
0&
0'
#397000000
1#
1'
#398000000
1"
0#
1&
0'
#399000000
1#
1'
#400000000
0!
0"
0#
0%
0&
0'
#401000000
1#
1'
#402000000
1"
0#
1&
0'
#403000000
1#
1'
#404000000
1!
0"
0#
1%
0&
0'
#405000000
1#
1'
#406000000
1"
0#
1&
0'
#407000000
1#
1'
#408000000
0!
0"
0#
0%
0&
0'
#409000000
1#
1'
#410000000
1"
0#
1&
0'
#411000000
1#
1'
#412000000
1!
0"
0#
1%
0&
0'
#413000000
1#
1'
#414000000
1"
0#
1&
0'
#415000000
1#
1'
#416000000
0!
0"
0#
0%
0&
0'
#417000000
1#
1'
#418000000
1"
0#
1&
0'
#419000000
1#
1'
#420000000
1!
0"
0#
1%
0&
0'
#421000000
1#
1'
#422000000
1"
0#
1&
0'
#423000000
1#
1'
#424000000
0!
0"
0#
0%
0&
0'
#425000000
1#
1'
#426000000
1"
0#
1&
0'
#427000000
1#
1'
#428000000
1!
0"
0#
1%
0&
0'
#429000000
1#
1'
#430000000
1"
0#
1&
0'
#431000000
1#
1'
#432000000
0!
0"
0#
0%
0&
0'
#433000000
1#
1'
#434000000
1"
0#
1&
0'
#435000000
1#
1'
#436000000
1!
0"
0#
1%
0&
0'
#437000000
1#
1'
#438000000
1"
0#
1&
0'
#439000000
1#
1'
#440000000
0!
0"
0#
0%
0&
0'
#441000000
1#
1'
#442000000
1"
0#
1&
0'
#443000000
1#
1'
#444000000
1!
0"
0#
1%
0&
0'
#445000000
1#
1'
#446000000
1"
0#
1&
0'
#447000000
1#
1'
#448000000
0!
0"
0#
0%
0&
0'
#449000000
1#
1'
#450000000
1"
0#
1&
0'
#451000000
1#
1'
#452000000
1!
0"
0#
1%
0&
0'
#453000000
1#
1'
#454000000
1"
0#
1&
0'
#455000000
1#
1'
#456000000
0!
0"
0#
0%
0&
0'
#457000000
1#
1'
#458000000
1"
0#
1&
0'
#459000000
1#
1'
#460000000
1!
0"
0#
1%
0&
0'
#461000000
1#
1'
#462000000
1"
0#
1&
0'
#463000000
1#
1'
#464000000
0!
0"
0#
0%
0&
0'
#465000000
1#
1'
#466000000
1"
0#
1&
0'
#467000000
1#
1'
#468000000
1!
0"
0#
1%
0&
0'
#469000000
1#
1'
#470000000
1"
0#
1&
0'
#471000000
1#
1'
#472000000
0!
0"
0#
0%
0&
0'
#473000000
1#
1'
#474000000
1"
0#
1&
0'
#475000000
1#
1'
#476000000
1!
0"
0#
1%
0&
0'
#477000000
1#
1'
#478000000
1"
0#
1&
0'
#479000000
1#
1'
#480000000
0!
0"
0#
0%
0&
0'
#481000000
1#
1'
#482000000
1"
0#
1&
0'
#483000000
1#
1'
#484000000
1!
0"
0#
1%
0&
0'
#485000000
1#
1'
#486000000
1"
0#
1&
0'
#487000000
1#
1'
#488000000
0!
0"
0#
0%
0&
0'
#489000000
1#
1'
#490000000
1"
0#
1&
0'
#491000000
1#
1'
#492000000
1!
0"
0#
1%
0&
0'
#493000000
1#
1'
#494000000
1"
0#
1&
0'
#495000000
1#
1'
#496000000
0!
0"
0#
0%
0&
0'
#497000000
1#
1'
#498000000
1"
0#
1&
0'
#499000000
1#
1'
#500000000
1!
0"
0#
1%
0&
0'
#501000000
1#
1'
#502000000
1"
0#
1&
0'
#503000000
1#
1'
#504000000
0!
0"
0#
0%
0&
0'
#505000000
1#
1'
#506000000
1"
0#
1&
0'
#507000000
1#
1'
#508000000
1!
0"
0#
1%
0&
0'
#509000000
1#
1'
#510000000
1"
0#
1&
0'
#511000000
1#
1'
#512000000
0!
0"
0#
0%
0&
0'
#513000000
1#
1'
#514000000
1"
0#
1&
0'
#515000000
1#
1'
#516000000
1!
0"
0#
1%
0&
0'
#517000000
1#
1'
#518000000
1"
0#
1&
0'
#519000000
1#
1'
#520000000
0!
0"
0#
0%
0&
0'
#521000000
1#
1'
#522000000
1"
0#
1&
0'
#523000000
1#
1'
#524000000
1!
0"
0#
1%
0&
0'
#525000000
1#
1'
#526000000
1"
0#
1&
0'
#527000000
1#
1'
#528000000
0!
0"
0#
0%
0&
0'
#529000000
1#
1'
#530000000
1"
0#
1&
0'
#531000000
1#
1'
#532000000
1!
0"
0#
1%
0&
0'
#533000000
1#
1'
#534000000
1"
0#
1&
0'
#535000000
1#
1'
#536000000
0!
0"
0#
0%
0&
0'
#537000000
1#
1'
#538000000
1"
0#
1&
0'
#539000000
1#
1'
#540000000
1!
0"
0#
1%
0&
0'
#541000000
1#
1'
#542000000
1"
0#
1&
0'
#543000000
1#
1'
#544000000
0!
0"
0#
0%
0&
0'
#545000000
1#
1'
#546000000
1"
0#
1&
0'
#547000000
1#
1'
#548000000
1!
0"
0#
1%
0&
0'
#549000000
1#
1'
#550000000
1"
0#
1&
0'
#551000000
1#
1'
#552000000
0!
0"
0#
0%
0&
0'
#553000000
1#
1'
#554000000
1"
0#
1&
0'
#555000000
1#
1'
#556000000
1!
0"
0#
1%
0&
0'
#557000000
1#
1'
#558000000
1"
0#
1&
0'
#559000000
1#
1'
#560000000
0!
0"
0#
0%
0&
0'
#561000000
1#
1'
#562000000
1"
0#
1&
0'
#563000000
1#
1'
#564000000
1!
0"
0#
1%
0&
0'
#565000000
1#
1'
#566000000
1"
0#
1&
0'
#567000000
1#
1'
#568000000
0!
0"
0#
0%
0&
0'
#569000000
1#
1'
#570000000
1"
0#
1&
0'
#571000000
1#
1'
#572000000
1!
0"
0#
1%
0&
0'
#573000000
1#
1'
#574000000
1"
0#
1&
0'
#575000000
1#
1'
#576000000
0!
0"
0#
0%
0&
0'
#577000000
1#
1'
#578000000
1"
0#
1&
0'
#579000000
1#
1'
#580000000
1!
0"
0#
1%
0&
0'
#581000000
1#
1'
#582000000
1"
0#
1&
0'
#583000000
1#
1'
#584000000
0!
0"
0#
0%
0&
0'
#585000000
1#
1'
#586000000
1"
0#
1&
0'
#587000000
1#
1'
#588000000
1!
0"
0#
1%
0&
0'
#589000000
1#
1'
#590000000
1"
0#
1&
0'
#591000000
1#
1'
#592000000
0!
0"
0#
0%
0&
0'
#593000000
1#
1'
#594000000
1"
0#
1&
0'
#595000000
1#
1'
#596000000
1!
0"
0#
1%
0&
0'
#597000000
1#
1'
#598000000
1"
0#
1&
0'
#599000000
1#
1'
#600000000
0!
0"
0#
0%
0&
0'
#601000000
1#
1'
#602000000
1"
0#
1&
0'
#603000000
1#
1'
#604000000
1!
0"
0#
1%
0&
0'
#605000000
1#
1'
#606000000
1"
0#
1&
0'
#607000000
1#
1'
#608000000
0!
0"
0#
0%
0&
0'
#609000000
1#
1'
#610000000
1"
0#
1&
0'
#611000000
1#
1'
#612000000
1!
0"
0#
1%
0&
0'
#613000000
1#
1'
#614000000
1"
0#
1&
0'
#615000000
1#
1'
#616000000
0!
0"
0#
0%
0&
0'
#617000000
1#
1'
#618000000
1"
0#
1&
0'
#619000000
1#
1'
#620000000
1!
0"
0#
1%
0&
0'
#621000000
1#
1'
#622000000
1"
0#
1&
0'
#623000000
1#
1'
#624000000
0!
0"
0#
0%
0&
0'
#625000000
1#
1'
#626000000
1"
0#
1&
0'
#627000000
1#
1'
#628000000
1!
0"
0#
1%
0&
0'
#629000000
1#
1'
#630000000
1"
0#
1&
0'
#631000000
1#
1'
#632000000
0!
0"
0#
0%
0&
0'
#633000000
1#
1'
#634000000
1"
0#
1&
0'
#635000000
1#
1'
#636000000
1!
0"
0#
1%
0&
0'
#637000000
1#
1'
#638000000
1"
0#
1&
0'
#639000000
1#
1'
#640000000
0!
0"
0#
0%
0&
0'
#641000000
1#
1'
#642000000
1"
0#
1&
0'
#643000000
1#
1'
#644000000
1!
0"
0#
1%
0&
0'
#645000000
1#
1'
#646000000
1"
0#
1&
0'
#647000000
1#
1'
#648000000
0!
0"
0#
0%
0&
0'
#649000000
1#
1'
#650000000
1"
0#
1&
0'
#651000000
1#
1'
#652000000
1!
0"
0#
1%
0&
0'
#653000000
1#
1'
#654000000
1"
0#
1&
0'
#655000000
1#
1'
#656000000
0!
0"
0#
0%
0&
0'
#657000000
1#
1'
#658000000
1"
0#
1&
0'
#659000000
1#
1'
#660000000
1!
0"
0#
1%
0&
0'
#661000000
1#
1'
#662000000
1"
0#
1&
0'
#663000000
1#
1'
#664000000
0!
0"
0#
0%
0&
0'
#665000000
1#
1'
#666000000
1"
0#
1&
0'
#667000000
1#
1'
#668000000
1!
0"
0#
1%
0&
0'
#669000000
1#
1'
#670000000
1"
0#
1&
0'
#671000000
1#
1'
#672000000
0!
0"
0#
0%
0&
0'
#673000000
1#
1'
#674000000
1"
0#
1&
0'
#675000000
1#
1'
#676000000
1!
0"
0#
1%
0&
0'
#677000000
1#
1'
#678000000
1"
0#
1&
0'
#679000000
1#
1'
#680000000
0!
0"
0#
0%
0&
0'
#681000000
1#
1'
#682000000
1"
0#
1&
0'
#683000000
1#
1'
#684000000
1!
0"
0#
1%
0&
0'
#685000000
1#
1'
#686000000
1"
0#
1&
0'
#687000000
1#
1'
#688000000
0!
0"
0#
0%
0&
0'
#689000000
1#
1'
#690000000
1"
0#
1&
0'
#691000000
1#
1'
#692000000
1!
0"
0#
1%
0&
0'
#693000000
1#
1'
#694000000
1"
0#
1&
0'
#695000000
1#
1'
#696000000
0!
0"
0#
0%
0&
0'
#697000000
1#
1'
#698000000
1"
0#
1&
0'
#699000000
1#
1'
#700000000
1!
0"
0#
1%
0&
0'
#701000000
1#
1'
#702000000
1"
0#
1&
0'
#703000000
1#
1'
#704000000
0!
0"
0#
0%
0&
0'
#705000000
1#
1'
#706000000
1"
0#
1&
0'
#707000000
1#
1'
#708000000
1!
0"
0#
1%
0&
0'
#709000000
1#
1'
#710000000
1"
0#
1&
0'
#711000000
1#
1'
#712000000
0!
0"
0#
0%
0&
0'
#713000000
1#
1'
#714000000
1"
0#
1&
0'
#715000000
1#
1'
#716000000
1!
0"
0#
1%
0&
0'
#717000000
1#
1'
#718000000
1"
0#
1&
0'
#719000000
1#
1'
#720000000
0!
0"
0#
0%
0&
0'
#721000000
1#
1'
#722000000
1"
0#
1&
0'
#723000000
1#
1'
#724000000
1!
0"
0#
1%
0&
0'
#725000000
1#
1'
#726000000
1"
0#
1&
0'
#727000000
1#
1'
#728000000
0!
0"
0#
0%
0&
0'
#729000000
1#
1'
#730000000
1"
0#
1&
0'
#731000000
1#
1'
#732000000
1!
0"
0#
1%
0&
0'
#733000000
1#
1'
#734000000
1"
0#
1&
0'
#735000000
1#
1'
#736000000
0!
0"
0#
0%
0&
0'
#737000000
1#
1'
#738000000
1"
0#
1&
0'
#739000000
1#
1'
#740000000
1!
0"
0#
1%
0&
0'
#741000000
1#
1'
#742000000
1"
0#
1&
0'
#743000000
1#
1'
#744000000
0!
0"
0#
0%
0&
0'
#745000000
1#
1'
#746000000
1"
0#
1&
0'
#747000000
1#
1'
#748000000
1!
0"
0#
1%
0&
0'
#749000000
1#
1'
#750000000
1"
0#
1&
0'
#751000000
1#
1'
#752000000
0!
0"
0#
0%
0&
0'
#753000000
1#
1'
#754000000
1"
0#
1&
0'
#755000000
1#
1'
#756000000
1!
0"
0#
1%
0&
0'
#757000000
1#
1'
#758000000
1"
0#
1&
0'
#759000000
1#
1'
#760000000
0!
0"
0#
0%
0&
0'
#761000000
1#
1'
#762000000
1"
0#
1&
0'
#763000000
1#
1'
#764000000
1!
0"
0#
1%
0&
0'
#765000000
1#
1'
#766000000
1"
0#
1&
0'
#767000000
1#
1'
#768000000
0!
0"
0#
0%
0&
0'
#769000000
1#
1'
#770000000
1"
0#
1&
0'
#771000000
1#
1'
#772000000
1!
0"
0#
1%
0&
0'
#773000000
1#
1'
#774000000
1"
0#
1&
0'
#775000000
1#
1'
#776000000
0!
0"
0#
0%
0&
0'
#777000000
1#
1'
#778000000
1"
0#
1&
0'
#779000000
1#
1'
#780000000
1!
0"
0#
1%
0&
0'
#781000000
1#
1'
#782000000
1"
0#
1&
0'
#783000000
1#
1'
#784000000
0!
0"
0#
0%
0&
0'
#785000000
1#
1'
#786000000
1"
0#
1&
0'
#787000000
1#
1'
#788000000
1!
0"
0#
1%
0&
0'
#789000000
1#
1'
#790000000
1"
0#
1&
0'
#791000000
1#
1'
#792000000
0!
0"
0#
0%
0&
0'
#793000000
1#
1'
#794000000
1"
0#
1&
0'
#795000000
1#
1'
#796000000
1!
0"
0#
1%
0&
0'
#797000000
1#
1'
#798000000
1"
0#
1&
0'
#799000000
1#
1'
#800000000
0!
0"
0#
0%
0&
0'
#801000000
1#
1'
#802000000
1"
0#
1&
0'
#803000000
1#
1'
#804000000
1!
0"
0#
1%
0&
0'
#805000000
1#
1'
#806000000
1"
0#
1&
0'
#807000000
1#
1'
#808000000
0!
0"
0#
0%
0&
0'
#809000000
1#
1'
#810000000
1"
0#
1&
0'
#811000000
1#
1'
#812000000
1!
0"
0#
1%
0&
0'
#813000000
1#
1'
#814000000
1"
0#
1&
0'
#815000000
1#
1'
#816000000
0!
0"
0#
0%
0&
0'
#817000000
1#
1'
#818000000
1"
0#
1&
0'
#819000000
1#
1'
#820000000
1!
0"
0#
1%
0&
0'
#821000000
1#
1'
#822000000
1"
0#
1&
0'
#823000000
1#
1'
#824000000
0!
0"
0#
0%
0&
0'
#825000000
1#
1'
#826000000
1"
0#
1&
0'
#827000000
1#
1'
#828000000
1!
0"
0#
1%
0&
0'
#829000000
1#
1'
#830000000
1"
0#
1&
0'
#831000000
1#
1'
#832000000
0!
0"
0#
0%
0&
0'
#833000000
1#
1'
#834000000
1"
0#
1&
0'
#835000000
1#
1'
#836000000
1!
0"
0#
1%
0&
0'
#837000000
1#
1'
#838000000
1"
0#
1&
0'
#839000000
1#
1'
#840000000
0!
0"
0#
0%
0&
0'
#841000000
1#
1'
#842000000
1"
0#
1&
0'
#843000000
1#
1'
#844000000
1!
0"
0#
1%
0&
0'
#845000000
1#
1'
#846000000
1"
0#
1&
0'
#847000000
1#
1'
#848000000
0!
0"
0#
0%
0&
0'
#849000000
1#
1'
#850000000
1"
0#
1&
0'
#851000000
1#
1'
#852000000
1!
0"
0#
1%
0&
0'
#853000000
1#
1'
#854000000
1"
0#
1&
0'
#855000000
1#
1'
#856000000
0!
0"
0#
0%
0&
0'
#857000000
1#
1'
#858000000
1"
0#
1&
0'
#859000000
1#
1'
#860000000
1!
0"
0#
1%
0&
0'
#861000000
1#
1'
#862000000
1"
0#
1&
0'
#863000000
1#
1'
#864000000
0!
0"
0#
0%
0&
0'
#865000000
1#
1'
#866000000
1"
0#
1&
0'
#867000000
1#
1'
#868000000
1!
0"
0#
1%
0&
0'
#869000000
1#
1'
#870000000
1"
0#
1&
0'
#871000000
1#
1'
#872000000
0!
0"
0#
0%
0&
0'
#873000000
1#
1'
#874000000
1"
0#
1&
0'
#875000000
1#
1'
#876000000
1!
0"
0#
1%
0&
0'
#877000000
1#
1'
#878000000
1"
0#
1&
0'
#879000000
1#
1'
#880000000
0!
0"
0#
0%
0&
0'
#881000000
1#
1'
#882000000
1"
0#
1&
0'
#883000000
1#
1'
#884000000
1!
0"
0#
1%
0&
0'
#885000000
1#
1'
#886000000
1"
0#
1&
0'
#887000000
1#
1'
#888000000
0!
0"
0#
0%
0&
0'
#889000000
1#
1'
#890000000
1"
0#
1&
0'
#891000000
1#
1'
#892000000
1!
0"
0#
1%
0&
0'
#893000000
1#
1'
#894000000
1"
0#
1&
0'
#895000000
1#
1'
#896000000
0!
0"
0#
0%
0&
0'
#897000000
1#
1'
#898000000
1"
0#
1&
0'
#899000000
1#
1'
