conditional/systemx.vhd
library IEEE;
use ieee.std_logic_1164.all; -- contains std_logic data types
use IEEE.numeric_std.all; -- contains function like "to_unsigned"

entity systemx is
    port (A, B, C : in std_logic;
        F : out std_logic);
end entity;

architecture systemx_arch of systemx is

    begin
        -- trigger process is assigned
        cmb1 : process (A, B, C) is

            -- define variable here
            variable ABC : std_logic_vector(2 downto 0) := "000";

            begin
                -- concatenate
                ABC := A & B & C;

                case (ABC) is
                    when "010" => F <= '1';
                    when "101" => F <= '1';
                    when "110" => F <= '1';
                    when others => F <= '0';
                end case;


        end process;

end architecture; -- systemx_arch

conditional/systemx_tb.vhd
library IEEE;
use ieee.std_logic_1164.all; -- contains std_logic data types
use IEEE.numeric_std.all; -- contains function like "to_unsigned"

entity systemx_tb is
    -- empty for testbenches
end entity;

architecture systemx_arch_tb of systemx_tb is
    component systemx is
        port (A, B, C : in std_logic;
            F : out std_logic);
    end component;

    signal signal_a, signal_b, signal_c, signal_f : std_logic;
    constant n : integer:= 3;

    begin
        comp : systemx port map (
            A => signal_a,
            B => signal_b,
            C => signal_c,
            F => signal_f
        );
    process
        variable i : integer;
        begin
            -- for i in 0 to 7 loop
            --     (signal_a, signal_b, signal_c) <= std_logic_vector(to_unsigned(i, n));
            --     report "signal_a: " & std_logic'image(signal_a);
            --     report "signal_b: " & std_logic'image(signal_b);
            --     report "signal_c: " & std_logic'image(signal_c);
            --     wait for 10 ns;
            --     report "nothing";
            --     report "signal_f: " & std_logic'image(signal_f);
            --     if(signal_a, signal_b, signal_c, signal)
            -- end loop;

            signal_a <= '0'; signal_b <= '0'; signal_c <= '0'; wait for 50 ns;
            report "input pattern 000; signal_f: " & std_logic'image(signal_f) severity NOTE;

            signal_a <= '0'; signal_b <= '0'; signal_c <= '1'; wait for 50 ns;
            report "input pattern 001; signal_f: " & std_logic'image(signal_f) severity NOTE;

            signal_a <= '0'; signal_b <= '1'; signal_c <= '0'; wait for 50 ns;
            report "input pattern 010; signal_f: " & std_logic'image(signal_f) severity NOTE;
            assert (signal_f='1') report "FAILED" severity NOTE;

            signal_a <= '0'; signal_b <= '1'; signal_c <= '1'; wait for 50 ns;
            report "input pattern 011; signal_f: " & std_logic'image(signal_f) severity NOTE;

            signal_a <= '1'; signal_b <= '0'; signal_c <= '0'; wait for 50 ns;
            report "input pattern 100; signal_f: " & std_logic'image(signal_f) severity NOTE;

            signal_a <= '1'; signal_b <= '0'; signal_c <= '1'; wait for 50 ns;
            report "input pattern 101; signal_f: " & std_logic'image(signal_f) severity NOTE;

            signal_a <= '1'; signal_b <= '1'; signal_c <= '0'; wait for 50 ns;
            report "input pattern 110; signal_f: " & std_logic'image(signal_f) severity NOTE;

            signal_a <= '1'; signal_b <= '1'; signal_c <= '1'; wait for 50 ns;
            report "input pattern 111; signal_f: " & std_logic'image(signal_f) severity NOTE;

    end process;

end architecture;

conditional/systemx_tb.vcd
$date
  Wed Apr  6 08:16:34 2022
$end
$version
  GHDL v0
$end
$timescale
  1 fs
$end
$scope module standard $end
$upscope $end
$scope module textio $end
$upscope $end
$scope module std_logic_1164 $end
$upscope $end
$scope module numeric_std $end
$upscope $end
$scope module systemx_tb $end
$var reg 1 ! signal_a $end
$var reg 1 " signal_b $end
$var reg 1 # signal_c $end
$var reg 1 $ signal_f $end
$scope module comp $end
$var reg 1 % a $end
$var reg 1 & b $end
$var reg 1 ' c $end
$var reg 1 ( f $end
$upscope $end
$upscope $end
$enddefinitions $end
#0
0!
0"
0#
0$
0%
0&
0'
0(
#50000000
1#
1'
#100000000
1"
0#
1$
1&
0'
1(
#150000000
1#
0$
1'
0(
#200000000
1!
0"
0#
1%
0&
0'
#250000000
1#
1$
1'
1(
#300000000
1"
0#
1&
0'
#350000000
1#
0$
1'
0(
#400000000
0!
0"
0#
0%
0&
0'
#450000000
1#
1'
#500000000
1"
0#
1$
1&
0'
1(
#550000000
1#
0$
1'
0(
#600000000
1!
0"
0#
1%
0&
0'
#650000000
1#
1$
1'
1(
#700000000
1"
0#
1&
0'
#750000000
1#
0$
1'
0(
#800000000
0!
0"
0#
0%
0&
0'
#850000000
1#
1'
#900000000
1"
0#
1$
1&
0'
1(
#950000000
1#
0$
1'
0(
#1000000000
1!
0"
0#
1%
0&
0'
#1050000000
1#
1$
1'
1(
#1100000000
1"
0#
1&
0'
#1150000000
1#
0$
1'
0(
#1200000000
0!
0"
0#
0%
0&
0'
#1250000000
1#
1'
#1300000000
1"
0#
1$
1&
0'
1(
#1350000000
1#
0$
1'
0(
#1400000000
1!
0"
0#
1%
0&
0'
#1450000000
1#
1$
1'
1(
#1500000000
1"
0#
1&
0'
#1550000000
1#
0$
1'
0(
#1600000000
0!
0"
0#
0%
0&
0'
#1650000000
1#
1'
#1700000000
1"
0#
1$
1&
0'
1(
#1750000000
1#
0$
1'
0(
#1800000000
1!
0"
0#
1%
0&
0'
#1850000000
1#
1$
1'
1(
#1900000000
1"
0#
1&
0'
#1950000000
1#
0$
1'
0(
#2000000000
0!
0"
0#
0%
0&
0'
#2050000000
1#
1'
#2100000000
1"
0#
1$
1&
0'
1(
#2150000000
1#
0$
1'
0(
#2200000000
1!
0"
0#
1%
0&
0'
#2250000000
1#
1$
1'
1(
#2300000000
1"
0#
1&
0'
#2350000000
1#
0$
1'
0(
#2400000000
0!
0"
0#
0%
0&
0'
#2450000000
1#
1'
#2500000000
1"
0#
1$
1&
0'
1(
#2550000000
1#
0$
1'
0(
#2600000000
1!
0"
0#
1%
0&
0'
#2650000000
1#
1$
1'
1(
#2700000000
1"
0#
1&
0'
#2750000000
1#
0$
1'
0(
#2800000000
0!
0"
0#
0%
0&
0'
#2850000000
1#
1'
#2900000000
1"
0#
1$
1&
0'
1(
#2950000000
1#
0$
1'
0(
#3000000000
1!
0"
0#
1%
0&
0'
#3050000000
1#
1$
1'
1(
#3100000000
1"
0#
1&
0'
#3150000000
1#
0$
1'
0(
#3200000000
0!
0"
0#
0%
0&
0'
#3250000000
1#
1'
#3300000000
1"
0#
1$
1&
0'
1(
#3350000000
1#
0$
1'
0(
#3400000000
1!
0"
0#
1%
0&
0'
#3450000000
1#
1$
1'
1(
#3500000000
1"
0#
1&
0'
#3550000000
1#
0$
1'
0(
#3600000000
0!
0"
0#
0%
0&
0'
#3650000000
1#
1'
#3700000000
1"
0#
1$
1&
0'
1(
#3750000000
1#
0$
1'
0(
#3800000000
1!
0"
0#
1%
0&
0'
#3850000000
1#
1$
1'
1(
#3900000000
1"
0#
1&
0'
#3950000000
1#
0$
1'
0(
#4000000000
0!
0"
0#
0%
0&
0'
#4050000000
1#
1'
#4100000000
1"
0#
1$
1&
0'
1(
#4150000000
1#
0$
1'
0(
#4200000000
1!
0"
0#
1%
0&
0'
#4250000000
1#
1$
1'
1(
#4300000000
1"
0#
1&
0'
#4350000000
1#
0$
1'
0(
#4400000000
0!
0"
0#
0%
0&
0'
#4450000000
1#
1'
#4500000000
1"
0#
1$
1&
0'
1(
#4550000000
1#
0$
1'
0(
#4600000000
1!
0"
0#
1%
0&
0'
#4650000000
1#
1$
1'
1(
#4700000000
1"
0#
1&
0'
#4750000000
1#
0$
1'
0(
#4800000000
0!
0"
0#
0%
0&
0'
#4850000000
1#
1'
#4900000000
1"
0#
1$
1&
0'
1(
#4950000000
1#
0$
1'
0(
#5000000000
1!
0"
0#
1%
0&
0'
#5050000000
1#
1$
1'
1(
#5100000000
1"
0#
1&
0'
#5150000000
1#
0$
1'
0(
#5200000000
0!
0"
0#
0%
0&
0'
#5250000000
1#
1'
#5300000000
1"
0#
1$
1&
0'
1(
#5350000000
1#
0$
1'
0(
#5400000000
1!
0"
0#
1%
0&
0'
#5450000000
1#
1$
1'
1(
#5500000000
1"
0#
1&
0'
#5550000000
1#
0$
1'
0(
#5600000000
0!
0"
0#
0%
0&
0'
#5650000000
1#
1'
#5700000000
1"
0#
1$
1&
0'
1(
#5750000000
1#
0$
1'
0(
#5800000000
1!
0"
0#
1%
0&
0'
#5850000000
1#
1$
1'
1(
#5900000000
1"
0#
1&
0'
#5950000000
1#
0$
1'
0(
#6000000000
0!
0"
0#
0%
0&
0'
#6050000000
1#
1'
#6100000000
1"
0#
1$
1&
0'
1(
#6150000000
1#
0$
1'
0(
#6200000000
1!
0"
0#
1%
0&
0'
#6250000000
1#
1$
1'
1(
#6300000000
1"
0#
1&
0'
#6350000000
1#
0$
1'
0(
#6400000000
0!
0"
0#
0%
0&
0'
#6450000000
1#
1'
#6500000000
1"
0#
1$
1&
0'
1(
#6550000000
1#
0$
1'
0(
#6600000000
1!
0"
0#
1%
0&
0'
#6650000000
1#
1$
1'
1(
#6700000000
1"
0#
1&
0'
#6750000000
1#
0$
1'
0(
#6800000000
0!
0"
0#
0%
0&
0'
#6850000000
1#
1'
#6900000000
1"
0#
1$
1&
0'
1(
#6950000000
1#
0$
1'
0(
#7000000000
1!
0"
0#
1%
0&
0'
#7050000000
1#
1$
1'
1(
#7100000000
1"
0#
1&
0'
#7150000000
1#
0$
1'
0(
#7200000000
0!
0"
0#
0%
0&
0'
#7250000000
1#
1'
#7300000000
1"
0#
1$
1&
0'
1(
#7350000000
1#
0$
1'
0(
#7400000000
1!
0"
0#
1%
0&
0'
#7450000000
1#
1$
1'
1(
#7500000000
1"
0#
1&
0'
#7550000000
1#
0$
1'
0(
#7600000000
0!
0"
0#
0%
0&
0'
#7650000000
1#
1'
#7700000000
1"
0#
1$
1&
0'
1(
#7750000000
1#
0$
1'
0(
#7800000000
1!
0"
0#
1%
0&
0'
#7850000000
1#
1$
1'
1(
#7900000000
1"
0#
1&
0'
#7950000000
1#
0$
1'
0(
#8000000000
0!
0"
0#
0%
0&
0'
#8050000000
1#
1'
#8100000000
1"
0#
1$
1&
0'
1(
#8150000000
1#
0$
1'
0(
#8200000000
1!
0"
0#
1%
0&
0'
#8250000000
1#
1$
1'
1(
#8300000000
1"
0#
1&
0'
#8350000000
1#
0$
1'
0(
#8400000000
0!
0"
0#
0%
0&
0'
#8450000000
1#
1'
#8500000000
1"
0#
1$
1&
0'
1(
#8550000000
1#
0$
1'
0(
#8600000000
1!
0"
0#
1%
0&
0'
#8650000000
1#
1$
1'
1(
#8700000000
1"
0#
1&
0'
#8750000000
1#
0$
1'
0(
#8800000000
0!
0"
0#
0%
0&
0'
#8850000000
1#
1'
#8900000000
1"
0#
1$
1&
0'
1(
#8950000000
1#
0$
1'
0(
#9000000000
1!
0"
0#
1%
0&
0'
#9050000000
1#
1$
1'
1(
#9100000000
1"
0#
1&
0'
#9150000000
1#
0$
1'
0(
#9200000000
0!
0"
0#
0%
0&
0'
#9250000000
1#
1'
#9300000000
1"
0#
1$
1&
0'
1(
#9350000000
1#
0$
1'
0(
#9400000000
1!
0"
0#
1%
0&
0'
#9450000000
1#
1$
1'
1(
#9500000000
1"
0#
1&
0'
#9550000000
1#
0$
1'
0(
#9600000000
0!
0"
0#
0%
0&
0'
#9650000000
1#
1'
#9700000000
1"
0#
1$
1&
0'
1(
#9750000000
1#
0$
1'
0(
#9800000000
1!
0"
0#
1%
0&
0'
#9850000000
1#
1$
1'
1(
#9900000000
1"
0#
1&
0'
#9950000000
1#
0$
1'
0(
#10000000000
0!
0"
0#
0%
0&
0'
#10050000000
1#
1'
#10100000000
1"
0#
1$
1&
0'
1(
#10150000000
1#
0$
1'
0(
#10200000000
1!
0"
0#
1%
0&
0'
#10250000000
1#
1$
1'
1(
#10300000000
1"
0#
1&
0'
#10350000000
1#
0$
1'
0(
#10400000000
0!
0"
0#
0%
0&
0'
#10450000000
1#
1'
#10500000000
1"
0#
1$
1&
0'
1(
#10550000000
1#
0$
1'
0(
#10600000000
1!
0"
0#
1%
0&
0'
#10650000000
1#
1$
1'
1(
#10700000000
1"
0#
1&
0'
#10750000000
1#
0$
1'
0(
#10800000000
0!
0"
0#
0%
0&
0'
#10850000000
1#
1'
#10900000000
1"
0#
1$
1&
0'
1(
#10950000000
1#
0$
1'
0(
#11000000000
1!
0"
0#
1%
0&
0'
#11050000000
1#
1$
1'
1(
#11100000000
1"
0#
1&
0'
#11150000000
1#
0$
1'
0(
#11200000000
0!
0"
0#
0%
0&
0'
#11250000000
1#
1'
#11300000000
1"
0#
1$
1&
0'
1(
#11350000000
1#
0$
1'
0(
#11400000000
1!
0"
0#
1%
0&
0'
#11450000000
1#
1$
1'
1(
#11500000000
1"
0#
1&
0'
#11550000000
1#
0$
1'
0(
#11600000000
0!
0"
0#
0%
0&
0'
#11650000000
1#
1'
#11700000000
1"
0#
1$
1&
0'
1(
#11750000000
1#
0$
1'
0(
#11800000000
1!
0"
0#
1%
0&
0'
#11850000000
1#
1$
1'
1(
#11900000000
1"
0#
1&
0'
#11950000000
1#
0$
1'
0(
#12000000000
0!
0"
0#
0%
0&
0'
#12050000000
1#
1'
#12100000000
1"
0#
1$
1&
0'
1(
#12150000000
1#
0$
1'
0(
#12200000000
1!
0"
0#
1%
0&
0'
#12250000000
1#
1$
1'
1(
#12300000000
1"
0#
1&
0'
#12350000000
1#
0$
1'
0(
#12400000000
0!
0"
0#
0%
0&
0'
#12450000000
1#
1'
#12500000000
1"
0#
1$
1&
0'
1(
#12550000000
1#
0$
1'
0(
#12600000000
1!
0"
0#
1%
0&
0'
#12650000000
1#
1$
1'
1(
#12700000000
1"
0#
1&
0'
#12750000000
1#
0$
1'
0(
#12800000000
0!
0"
0#
0%
0&
0'
#12850000000
1#
1'
#12900000000
1"
0#
1$
1&
0'
1(
#12950000000
1#
0$
1'
0(
#13000000000
1!
0"
0#
1%
0&
0'
#13050000000
1#
1$
1'
1(
#13100000000
1"
0#
1&
0'
#13150000000
1#
0$
1'
0(
#13200000000
0!
0"
0#
0%
0&
0'
#13250000000
1#
1'
#13300000000
1"
0#
1$
1&
0'
1(
#13350000000
1#
0$
1'
0(
#13400000000
1!
0"
0#
1%
0&
0'
#13450000000
1#
1$
1'
1(
#13500000000
1"
0#
1&
0'
#13550000000
1#
0$
1'
0(
#13600000000
0!
0"
0#
0%
0&
0'
#13650000000
1#
1'
#13700000000
1"
0#
1$
1&
0'
1(
#13750000000
1#
0$
1'
0(
#13800000000
1!
0"
0#
1%
0&
0'
#13850000000
1#
1$
1'
1(
#13900000000
1"
0#
1&
0'
#13950000000
1#
0$
1'
0(
#14000000000
0!
0"
0#
0%
0&
0'
#14050000000
1#
1'
#14100000000
1"
0#
1$
1&
0'
1(
#14150000000
1#
0$
1'
0(
#14200000000
1!
0"
0#
1%
0&
0'
#14250000000
1#
1$
1'
1(
#14300000000
1"
0#
1&
0'
#14350000000
1#
0$
1'
0(
#14400000000
0!
0"
0#
0%
0&
0'
#14450000000
1#
1'
#14500000000
1"
0#
1$
1&
0'
1(
#14550000000
1#
0$
1'
0(
#14600000000
1!
0"
0#
1%
0&
0'
#14650000000
1#
1$
1'
1(
#14700000000
1"
0#
1&
0'
#14750000000
1#
0$
1'
0(
#14800000000
0!
0"
0#
0%
0&
0'
#14850000000
1#
1'
#14900000000
1"
0#
1$
1&
0'
1(
#14950000000
1#
0$
1'
0(
#15000000000
1!
0"
0#
1%
0&
0'
#15050000000
1#
1$
1'
1(
#15100000000
1"
0#
1&
0'
#15150000000
1#
0$
1'
0(
#15200000000
0!
0"
0#
0%
0&
0'
#15250000000
1#
1'
#15300000000
1"
0#
1$
1&
0'
1(
#15350000000
1#
0$
1'
0(
#15400000000
1!
0"
0#
1%
0&
0'
#15450000000
1#
1$
1'
1(
#15500000000
1"
0#
1&
0'
#15550000000
1#
0$
1'
0(
#15600000000
0!
0"
0#
0%
0&
0'
#15650000000
1#
1'
#15700000000
1"
0#
1$
1&
0'
1(
#15750000000
1#
0$
1'
0(
#15800000000
1!
0"
0#
1%
0&
0'
#15850000000
1#
1$
1'
1(
#15900000000
1"
0#
1&
0'
#15950000000
1#
0$
1'
0(
#16000000000
0!
0"
0#
0%
0&
0'
#16050000000
1#
1'
#16100000000
1"
0#
1$
1&
0'
1(
#16150000000
1#
0$
1'
0(
#16200000000
1!
0"
0#
1%
0&
0'
#16250000000
1#
1$
1'
1(
#16300000000
1"
0#
1&
0'
#16350000000
1#
0$
1'
0(
#16400000000
0!
0"
0#
0%
0&
0'
#16450000000
1#
1'
#16500000000
1"
0#
1$
1&
0'
1(
#16550000000
1#
0$
1'
0(
#16600000000
1!
0"
0#
1%
0&
0'
#16650000000
1#
1$
1'
1(
#16700000000
1"
0#
1&
0'
#16750000000
1#
0$
1'
0(
#16800000000
0!
0"
0#
0%
0&
0'
#16850000000
1#
1'
#16900000000
1"
0#
1$
1&
0'
1(
#16950000000
1#
0$
1'
0(
#17000000000
1!
0"
0#
1%
0&
0'
#17050000000
1#
1$
1'
1(
#17100000000
1"
0#
1&
0'
#17150000000
1#
0$
1'
0(
#17200000000
0!
0"
0#
0%
0&
0'
#17250000000
1#
1'
#17300000000
1"
0#
1$
1&
0'
1(
#17350000000
1#
0$
1'
0(
#17400000000
1!
0"
0#
1%
0&
0'
#17450000000
1#
1$
1'
1(
#17500000000
1"
0#
1&
0'
#17550000000
1#
0$
1'
0(
#17600000000
0!
0"
0#
0%
0&
0'
#17650000000
1#
1'
#17700000000
1"
0#
1$
1&
0'
1(
#17750000000
1#
0$
1'
0(
#17800000000
1!
0"
0#
1%
0&
0'
#17850000000
1#
1$
1'
1(
#17900000000
1"
0#
1&
0'
#17950000000
1#
0$
1'
0(
#18000000000
0!
0"
0#
0%
0&
0'
#18050000000
1#
1'
#18100000000
1"
0#
1$
1&
0'
1(
#18150000000
1#
0$
1'
0(
#18200000000
1!
0"
0#
1%
0&
0'
#18250000000
1#
1$
1'
1(
#18300000000
1"
0#
1&
0'
#18350000000
1#
0$
1'
0(
#18400000000
0!
0"
0#
0%
0&
0'
#18450000000
1#
1'
#18500000000
1"
0#
1$
1&
0'
1(
#18550000000
1#
0$
1'
0(
#18600000000
1!
0"
0#
1%
0&
0'
#18650000000
1#
1$
1'
1(
#18700000000
1"
0#
1&
0'
#18750000000
1#
0$
1'
0(
#18800000000
0!
0"
0#
0%
0&
0'
#18850000000
1#
1'
#18900000000
1"
0#
1$
1&
0'
1(
#18950000000
1#
0$
1'
0(
#19000000000
1!
0"
0#
1%
0&
0'
#19050000000
1#
1$
1'
1(
#19100000000
1"
0#
1&
0'
#19150000000
1#
0$
1'
0(
#19200000000
0!
0"
0#
0%
0&
0'
#19250000000
1#
1'
#19300000000
1"
0#
1$
1&
0'
1(
#19350000000
1#
0$
1'
0(
#19400000000
1!
0"
0#
1%
0&
0'
#19450000000
1#
1$
1'
1(
#19500000000
1"
0#
1&
0'
#19550000000
1#
0$
1'
0(
#19600000000
0!
0"
0#
0%
0&
0'
#19650000000
1#
1'
#19700000000
1"
0#
1$
1&
0'
1(
#19750000000
1#
0$
1'
0(
#19800000000
1!
0"
0#
1%
0&
0'
#19850000000
1#
1$
1'
1(
#19900000000
1"
0#
1&
0'
#19950000000
1#
0$
1'
0(
#20000000000
0!
0"
0#
0%
0&
0'
#20050000000
1#
1'
#20100000000
1"
0#
1$
1&
0'
1(
#20150000000
1#
0$
1'
0(
#20200000000
1!
0"
0#
1%
0&
0'
#20250000000
1#
1$
1'
1(
#20300000000
1"
0#
1&
0'
#20350000000
1#
0$
1'
0(
#20400000000
0!
0"
0#
0%
0&
0'
#20450000000
1#
1'
#20500000000
1"
0#
1$
1&
0'
1(
#20550000000
1#
0$
1'
0(
#20600000000
1!
0"
0#
1%
0&
0'
#20650000000
1#
1$
1'
1(
#20700000000
1"
0#
1&
0'
#20750000000
1#
0$
1'
0(
#20800000000
0!
0"
0#
0%
0&
0'
#20850000000
1#
1'
#20900000000
1"
0#
1$
1&
0'
1(
#20950000000
1#
0$
1'
0(
#21000000000
1!
0"
0#
1%
0&
0'
#21050000000
1#
1$
1'
1(
#21100000000
1"
0#
1&
0'
#21150000000
1#
0$
1'
0(
#21200000000
0!
0"
0#
0%
0&
0'
#21250000000
1#
1'
#21300000000
1"
0#
1$
1&
0'
1(
#21350000000
1#
0$
1'
0(
#21400000000
1!
0"
0#
1%
0&
0'
#21450000000
1#
1$
1'
1(
#21500000000
1"
0#
1&
0'
#21550000000
1#
0$
1'
0(
#21600000000
0!
0"
0#
0%
0&
0'
#21650000000
1#
1'
#21700000000
1"
0#
1$
1&
0'
1(
#21750000000
1#
0$
1'
0(
#21800000000
1!
0"
0#
1%
0&
0'
#21850000000
1#
1$
1'
1(
#21900000000
1"
0#
1&
0'
#21950000000
1#
0$
1'
0(
#22000000000
0!
0"
0#
0%
0&
0'
#22050000000
1#
1'
#22100000000
1"
0#
1$
1&
0'
1(
#22150000000
1#
0$
1'
0(
#22200000000
1!
0"
0#
1%
0&
0'
#22250000000
1#
1$
1'
1(
#22300000000
1"
0#
1&
0'
#22350000000
1#
0$
1'
0(
#22400000000
0!
0"
0#
0%
0&
0'
#22450000000
1#
1'
#22500000000
1"
0#
1$
1&
0'
1(
#22550000000
1#
0$
1'
0(
#22600000000
1!
0"
0#
1%
0&
0'
#22650000000
1#
1$
1'
1(
#22700000000
1"
0#
1&
0'
#22750000000
1#
0$
1'
0(
#22800000000
0!
0"
0#
0%
0&
0'
#22850000000
1#
1'
#22900000000
1"
0#
1$
1&
0'
1(
#22950000000
1#
0$
1'
0(
#23000000000
1!
0"
0#
1%
0&
0'
#23050000000
1#
1$
1'
1(
#23100000000
1"
0#
1&
0'
#23150000000
1#
0$
1'
0(
#23200000000
0!
0"
0#
0%
0&
0'
#23250000000
1#
1'
#23300000000
1"
0#
1$
1&
0'
1(
#23350000000
1#
0$
1'
0(
#23400000000
1!
0"
0#
1%
0&
0'
#23450000000
1#
1$
1'
1(
#23500000000
1"
0#
1&
0'
#23550000000
1#
0$
1'
0(
#23600000000
0!
0"
0#
0%
0&
0'
#23650000000
1#
1'
#23700000000
1"
0#
1$
1&
0'
1(
#23750000000
1#
0$
1'
0(
#23800000000
1!
0"
0#
1%
0&
0'
#23850000000
1#
1$
1'
1(
#23900000000
1"
0#
1&
0'
#23950000000
1#
0$
1'
0(
#24000000000
0!
0"
0#
0%
0&
0'
#24050000000
1#
1'
#24100000000
1"
0#
1$
1&
0'
1(
#24150000000
1#
0$
1'
0(
#24200000000
1!
0"
0#
1%
0&
0'
#24250000000
1#
1$
1'
1(
#24300000000
1"
0#
1&
0'
#24350000000
1#
0$
1'
0(
#24400000000
0!
0"
0#
0%
0&
0'
#24450000000
1#
1'
#24500000000
1"
0#
1$
1&
0'
1(
#24550000000
1#
0$
1'
0(
#24600000000
1!
0"
0#
1%
0&
0'
#24650000000
1#
1$
1'
1(
#24700000000
1"
0#
1&
0'
#24750000000
1#
0$
1'
0(
#24800000000
0!
0"
0#
0%
0&
0'
#24850000000
1#
1'
#24900000000
1"
0#
1$
1&
0'
1(
#24950000000
1#
0$
1'
0(
#25000000000
1!
0"
0#
1%
0&
0'
#25050000000
1#
1$
1'
1(
#25100000000
1"
0#
1&
0'
#25150000000
1#
0$
1'
0(
#25200000000
0!
0"
0#
0%
0&
0'
#25250000000
1#
1'
#25300000000
1"
0#
1$
1&
0'
1(
#25350000000
1#
0$
1'
0(
#25400000000
1!
0"
0#
1%
0&
0'
#25450000000
1#
1$
1'
1(
#25500000000
1"
0#
1&
0'
#25550000000
1#
0$
1'
0(
#25600000000
0!
0"
0#
0%
0&
0'
#25650000000
1#
1'
#25700000000
1"
0#
1$
1&
0'
1(
#25750000000
1#
0$
1'
0(
#25800000000
1!
0"
0#
1%
0&
0'
#25850000000
1#
1$
1'
1(
#25900000000
1"
0#
1&
0'
#25950000000
1#
0$
1'
0(
#26000000000
0!
0"
0#
0%
0&
0'
#26050000000
1#
1'
#26100000000
1"
0#
1$
1&
0'
1(
#26150000000
1#
0$
1'
0(
#26200000000
1!
0"
0#
1%
0&
0'
#26250000000
1#
1$
1'
1(
#26300000000
1"
0#
1&
0'
#26350000000
1#
0$
1'
0(
#26400000000
0!
0"
0#
0%
0&
0'
#26450000000
1#
1'
#26500000000
1"
0#
1$
1&
0'
1(
#26550000000
1#
0$
1'
0(
#26600000000
1!
0"
0#
1%
0&
0'
#26650000000
1#
1$
1'
1(
#26700000000
1"
0#
1&
0'
#26750000000
1#
0$
1'
0(
#26800000000
0!
0"
0#
0%
0&
0'
#26850000000
1#
1'
#26900000000
1"
0#
1$
1&
0'
1(
#26950000000
1#
0$
1'
0(
#27000000000
1!
0"
0#
1%
0&
0'
#27050000000
1#
1$
1'
1(
#27100000000
1"
0#
1&
0'
#27150000000
1#
0$
1'
0(
#27200000000
0!
0"
0#
0%
0&
0'
#27250000000
1#
1'
#27300000000
1"
0#
1$
1&
0'
1(
#27350000000
1#
0$
1'
0(
#27400000000
1!
0"
0#
1%
0&
0'
#27450000000
1#
1$
1'
1(
#27500000000
1"
0#
1&
0'
#27550000000
1#
0$
1'
0(
#27600000000
0!
0"
0#
0%
0&
0'
#27650000000
1#
1'
#27700000000
1"
0#
1$
1&
0'
1(
#27750000000
1#
0$
1'
0(
#27800000000
1!
0"
0#
1%
0&
0'
#27850000000
1#
1$
1'
1(
#27900000000
1"
0#
1&
0'
#27950000000
1#
0$
1'
0(
#28000000000
0!
0"
0#
0%
0&
0'
#28050000000
1#
1'
#28100000000
1"
0#
1$
1&
0'
1(
#28150000000
1#
0$
1'
0(
#28200000000
1!
0"
0#
1%
0&
0'
#28250000000
1#
1$
1'
1(
#28300000000
1"
0#
1&
0'
#28350000000
1#
0$
1'
0(
#28400000000
0!
0"
0#
0%
0&
0'
#28450000000
1#
1'
#28500000000
1"
0#
1$
1&
0'
1(
#28550000000
1#
0$
1'
0(
#28600000000
1!
0"
0#
1%
0&
0'
#28650000000
1#
1$
1'
1(
#28700000000
1"
0#
1&
0'
#28750000000
1#
0$
1'
0(
#28800000000
0!
0"
0#
0%
0&
0'
#28850000000
1#
1'
#28900000000
1"
0#
1$
1&
0'
1(
#28950000000
1#
0$
1'
0(
#29000000000
1!
0"
0#
1%
0&
0'
#29050000000
1#
1$
1'
1(
#29100000000
1"
0#
1&
0'
#29150000000
1#
0$
1'
0(
#29200000000
0!
0"
0#
0%
0&
0'
#29250000000
1#
1'
#29300000000
1"
0#
1$
1&
0'
1(
#29350000000
1#
0$
1'
0(
#29400000000
1!
0"
0#
1%
0&
0'
#29450000000
1#
1$
1'
1(
#29500000000
1"
0#
1&
0'
#29550000000
1#
0$
1'
0(
#29600000000
0!
0"
0#
0%
0&
0'
#29650000000
1#
1'
#29700000000
1"
0#
1$
1&
0'
1(
#29750000000
1#
0$
1'
0(
#29800000000
1!
0"
0#
1%
0&
0'
#29850000000
1#
1$
1'
1(
#29900000000
1"
0#
1&
0'
#29950000000
1#
0$
1'
0(
#30000000000
0!
0"
0#
0%
0&
0'
#30050000000
1#
1'
#30100000000
1"
0#
1$
1&
0'
1(
#30150000000
1#
0$
1'
0(
#30200000000
1!
0"
0#
1%
0&
0'
#30250000000
1#
1$
1'
1(
#30300000000
1"
0#
1&
0'
#30350000000
1#
0$
1'
0(
#30400000000
0!
0"
0#
0%
0&
0'
#30450000000
1#
1'
#30500000000
1"
0#
1$
1&
0'
1(
#30550000000
1#
0$
1'
0(
#30600000000
1!
0"
0#
1%
0&
0'
#30650000000
1#
1$
1'
1(
#30700000000
1"
0#
1&
0'
#30750000000
1#
0$
1'
0(
#30800000000
0!
0"
0#
0%
0&
0'
#30850000000
1#
1'
#30900000000
1"
0#
1$
1&
0'
1(
#30950000000
1#
0$
1'
0(
#31000000000
1!
0"
0#
1%
0&
0'
#31050000000
1#
1$
1'
1(
#31100000000
1"
0#
1&
0'
#31150000000
1#
0$
1'
0(
#31200000000
0!
0"
0#
0%
0&
0'
#31250000000
1#
1'
#31300000000
1"
0#
1$
1&
0'
1(
#31350000000
1#
0$
1'
0(
#31400000000
1!
0"
0#
1%
0&
0'
#31450000000
1#
1$
1'
1(
#31500000000
1"
0#
1&
0'
#31550000000
1#
0$
1'
0(
#31600000000
0!
0"
0#
0%
0&
0'
#31650000000
1#
1'
#31700000000
1"
0#
1$
1&
0'
1(
#31750000000
1#
0$
1'
0(
#31800000000
1!
0"
0#
1%
0&
0'
#31850000000
1#
1$
1'
1(
#31900000000
1"
0#
1&
0'
#31950000000
1#
0$
1'
0(
#32000000000
0!
0"
0#
0%
0&
0'
#32050000000
1#
1'
#32100000000
1"
0#
1$
1&
0'
1(
#32150000000
1#
0$
1'
0(
#32200000000
1!
0"
0#
1%
0&
0'
#32250000000
1#
1$
1'
1(
#32300000000
1"
0#
1&
0'
#32350000000
1#
0$
1'
0(
#32400000000
0!
0"
0#
0%
0&
0'
#32450000000
1#
1'
#32500000000
1"
0#
1$
1&
0'
1(
#32550000000
1#
0$
1'
0(
#32600000000
1!
0"
0#
1%
0&
0'
#32650000000
1#
1$
1'
1(
#32700000000
1"
0#
1&
0'
#32750000000
1#
0$
1'
0(
#32800000000
0!
0"
0#
0%
0&
0'
#32850000000
1#
1'
#32900000000
1"
0#
1$
1&
0'
1(
#32950000000
1#
0$
1'
0(
#33000000000
1!
0"
0#
1%
0&
0'
#33050000000
1#
1$
1'
1(
#33100000000
1"
0#
1&
0'
#33150000000
1#
0$
1'
0(
#33200000000
0!
0"
0#
0%
0&
0'
#33250000000
1#
1'
#33300000000
1"
0#
1$
1&
0'
1(
#33350000000
1#
0$
1'
0(
#33400000000
1!
0"
0#
1%
0&
0'
#33450000000
1#
1$
1'
1(
#33500000000
1"
0#
1&
0'
#33550000000
1#
0$
1'
0(
#33600000000
0!
0"
0#
0%
0&
0'
#33650000000
1#
1'
#33700000000
1"
0#
1$
1&
0'
1(
#33750000000
1#
0$
1'
0(
#33800000000
1!
0"
0#
1%
0&
0'
#33850000000
1#
1$
1'
1(
#33900000000
1"
0#
1&
0'
#33950000000
1#
0$
1'
0(
