systemx/systemx.vhd
library IEEE;
use ieee.std_logic_1164.all;

entity systemx is
    port (A, B, C : in std_logic;
        F : out std_logic);
end entity;

architecture systemx_arch of systemx is

    begin
        -- naming process cmb1
        cmb1 : process (A, B, C)
            
            begin
                if   (A = '0' and B = '1' and C = '0') then F <= '1';
                elsif   (A = '1' and B = '0' and C = '0') then F <= '1';
                elsif   (A = '1' and B = '1' and C = '1') then F <= '1';
                else    F <= '0';
                end if;
        end process;

end architecture;

systemx/systemx_tb.vhd
library IEEE;
use ieee.std_logic_1164.all; -- contains std_logic data types
use IEEE.numeric_std.all; -- contains function like "to_unsigned"

entity systemx_tb is
    -- empty for testbenches
end entity;

architecture systemx_arch_tb of systemx_tb is
    component systemx is
        port (A, B, C : in std_logic;
            F : out std_logic);
    end component;

    signal signal_a, signal_b, signal_c, signal_f : std_logic;
    constant n : integer:= 3;

    begin
        comp : systemx port map (
            A => signal_a,
            B => signal_b,
            C => signal_c,
            F => signal_f
        );
    process
        variable i : integer;
        begin
            for i in 0 to 7 loop
                (signal_a,signal_b,signal_c) <= std_logic_vector(to_unsigned(i, n));
                report "signal_a: " & std_logic'image(signal_a);
                report "signal_b: " & std_logic'image(signal_b);
                report "signal_c: " & std_logic'image(signal_c);
                wait for 10 ns;
                report "nothing";
                report "signal_f: " & std_logic'image(signal_f);
            end loop;
    end process;

end architecture;

systemx/system_tb.vcd
$date
  Wed Apr  6 05:22:17 2022
$end
$version
  GHDL v0
$end
$timescale
  1 fs
$end
$scope module standard $end
$upscope $end
$scope module textio $end
$upscope $end
$scope module std_logic_1164 $end
$upscope $end
$scope module numeric_std $end
$upscope $end
$scope module systemx_tb $end
$var reg 1 ! signal_a $end
$var reg 1 " signal_b $end
$var reg 1 # signal_c $end
$var reg 1 $ signal_f $end
$scope module comp $end
$var reg 1 % a $end
$var reg 1 & b $end
$var reg 1 ' c $end
$var reg 1 ( f $end
$upscope $end
$upscope $end
$enddefinitions $end
#0
0!
0"
0#
0$
0%
0&
0'
0(
#10000000
1#
1'
#20000000
1"
0#
1$
1&
0'
1(
#30000000
1#
0$
1'
0(
#40000000
1!
0"
0#
1$
1%
0&
0'
1(
#50000000
1#
0$
1'
0(
#60000000
1"
0#
1&
0'
#70000000
1#
1$
1'
1(
#80000000
0!
0"
0#
0$
0%
0&
0'
0(
#90000000
1#
1'
#100000000
1"
0#
1$
1&
0'
1(
#110000000
1#
0$
1'
0(
#120000000
1!
0"
0#
1$
1%
0&
0'
1(
#130000000
1#
0$
1'
0(
#140000000
1"
0#
1&
0'
#150000000
1#
1$
1'
1(
#160000000
0!
0"
0#
0$
0%
0&
0'
0(
#170000000
1#
1'
#180000000
1"
0#
1$
1&
0'
1(
#190000000
1#
0$
1'
0(
#200000000
1!
0"
0#
1$
1%
0&
0'
1(
#210000000
1#
0$
1'
0(
#220000000
1"
0#
1&
0'
#230000000
1#
1$
1'
1(
#240000000
0!
0"
0#
0$
0%
0&
0'
0(
#250000000
1#
1'
#260000000
1"
0#
1$
1&
0'
1(
#270000000
1#
0$
1'
0(
#280000000
1!
0"
0#
1$
1%
0&
0'
1(
#290000000
1#
0$
1'
0(
#300000000
1"
0#
1&
0'
#310000000
1#
1$
1'
1(
#320000000
0!
0"
0#
0$
0%
0&
0'
0(
#330000000
1#
1'
#340000000
1"
0#
1$
1&
0'
1(
#350000000
1#
0$
1'
0(
#360000000
1!
0"
0#
1$
1%
0&
0'
1(
#370000000
1#
0$
1'
0(
#380000000
1"
0#
1&
0'
#390000000
1#
1$
1'
1(
#400000000
0!
0"
0#
0$
0%
0&
0'
0(
#410000000
1#
1'
#420000000
1"
0#
1$
1&
0'
1(
#430000000
1#
0$
1'
0(
#440000000
1!
0"
0#
1$
1%
0&
0'
1(
#450000000
1#
0$
1'
0(
#460000000
1"
0#
1&
0'
#470000000
1#
1$
1'
1(
#480000000
0!
0"
0#
0$
0%
0&
0'
0(
#490000000
1#
1'
#500000000
1"
0#
1$
1&
0'
1(
#510000000
1#
0$
1'
0(
#520000000
1!
0"
0#
1$
1%
0&
0'
1(
#530000000
1#
0$
1'
0(
#540000000
1"
0#
1&
0'
#550000000
1#
1$
1'
1(
#560000000
0!
0"
0#
0$
0%
0&
0'
0(
#570000000
1#
1'
#580000000
1"
0#
1$
1&
0'
1(
#590000000
1#
0$
1'
0(
#600000000
1!
0"
0#
1$
1%
0&
0'
1(
#610000000
1#
0$
1'
0(
#620000000
1"
0#
1&
0'
#630000000
1#
1$
1'
1(
#640000000
0!
0"
0#
0$
0%
0&
0'
0(
#650000000
1#
1'
#660000000
1"
0#
1$
1&
0'
1(
#670000000
1#
0$
1'
0(
#680000000
1!
0"
0#
1$
1%
0&
0'
1(
#690000000
1#
0$
1'
0(
#700000000
1"
0#
1&
0'
#710000000
1#
1$
1'
1(
#720000000
0!
0"
0#
0$
0%
0&
0'
0(
#730000000
1#
1'
#740000000
1"
0#
1$
1&
0'
1(
#750000000
1#
0$
1'
0(
#760000000
1!
0"
0#
1$
1%
0&
0'
1(
#770000000
1#
0$
1'
0(
#780000000
1"
0#
1&
0'
#790000000
1#
1$
1'
1(
#800000000
0!
0"
0#
0$
0%
0&
0'
0(
#810000000
1#
1'
#820000000
1"
0#
1$
1&
0'
1(
#830000000
1#
0$
1'
0(
#840000000
1!
0"
0#
1$
1%
0&
0'
1(
#850000000
1#
0$
1'
0(
#860000000
1"
0#
1&
0'
#870000000
1#
1$
1'
1(
#880000000
0!
0"
0#
0$
0%
0&
0'
0(
#890000000
1#
1'
#900000000
1"
0#
1$
1&
0'
1(
#910000000
1#
0$
1'
0(
#920000000
1!
0"
0#
1$
1%
0&
0'
1(
#930000000
1#
0$
1'
0(
#940000000
1"
0#
1&
0'
#950000000
1#
1$
1'
1(
#960000000
0!
0"
0#
0$
0%
0&
0'
0(
#970000000
1#
1'
#980000000
1"
0#
1$
1&
0'
1(
#990000000
1#
0$
1'
0(
#1000000000
1!
0"
0#
1$
1%
0&
0'
1(
#1010000000
1#
0$
1'
0(
#1020000000
1"
0#
1&
0'
#1030000000
1#
1$
1'
1(
#1040000000
0!
0"
0#
0$
0%
0&
0'
0(
#1050000000
1#
1'
#1060000000
1"
0#
1$
1&
0'
1(
#1070000000
1#
0$
1'
0(
#1080000000
1!
0"
0#
1$
1%
0&
0'
1(
#1090000000
1#
0$
1'
0(
#1100000000
1"
0#
1&
0'
#1110000000
1#
1$
1'
1(
#1120000000
0!
0"
0#
0$
0%
0&
0'
0(
#1130000000
1#
1'
#1140000000
1"
0#
1$
1&
0'
1(
#1150000000
1#
0$
1'
0(
#1160000000
1!
0"
0#
1$
1%
0&
0'
1(
#1170000000
1#
0$
1'
0(
#1180000000
1"
0#
1&
0'
#1190000000
1#
1$
1'
1(
#1200000000
0!
0"
0#
0$
0%
0&
0'
0(
#1210000000
1#
1'
#1220000000
1"
0#
1$
1&
0'
1(
#1230000000
1#
0$
1'
0(
#1240000000
1!
0"
0#
1$
1%
0&
0'
1(
#1250000000
1#
0$
1'
0(
#1260000000
1"
0#
1&
0'
#1270000000
1#
1$
1'
1(
#1280000000
0!
0"
0#
0$
0%
0&
0'
0(
#1290000000
1#
1'
#1300000000
1"
0#
1$
1&
0'
1(
#1310000000
1#
0$
1'
0(
#1320000000
1!
0"
0#
1$
1%
0&
0'
1(
#1330000000
1#
0$
1'
0(
#1340000000
1"
0#
1&
0'
#1350000000
1#
1$
1'
1(
#1360000000
0!
0"
0#
0$
0%
0&
0'
0(
#1370000000
1#
1'
#1380000000
1"
0#
1$
1&
0'
1(
#1390000000
1#
0$
1'
0(
#1400000000
1!
0"
0#
1$
1%
0&
0'
1(
#1410000000
1#
0$
1'
0(
#1420000000
1"
0#
1&
0'
#1430000000
1#
1$
1'
1(
#1440000000
0!
0"
0#
0$
0%
0&
0'
0(
#1450000000
1#
1'
#1460000000
1"
0#
1$
1&
0'
1(
#1470000000
1#
0$
1'
0(
#1480000000
1!
0"
0#
1$
1%
0&
0'
1(
#1490000000
1#
0$
1'
0(
#1500000000
1"
0#
1&
0'
#1510000000
1#
1$
1'
1(
#1520000000
0!
0"
0#
0$
0%
0&
0'
0(
#1530000000
1#
1'
#1540000000
1"
0#
1$
1&
0'
1(
#1550000000
1#
0$
1'
0(
#1560000000
1!
0"
0#
1$
1%
0&
0'
1(
#1570000000
1#
0$
1'
0(
#1580000000
1"
0#
1&
0'
#1590000000
1#
1$
1'
1(
#1600000000
0!
0"
0#
0$
0%
0&
0'
0(
#1610000000
1#
1'
#1620000000
1"
0#
1$
1&
0'
1(
#1630000000
1#
0$
1'
0(
#1640000000
1!
0"
0#
1$
1%
0&
0'
1(
#1650000000
1#
0$
1'
0(
#1660000000
1"
0#
1&
0'
#1670000000
1#
1$
1'
1(
#1680000000
0!
0"
0#
0$
0%
0&
0'
0(
#1690000000
1#
1'
#1700000000
1"
0#
1$
1&
0'
1(
#1710000000
1#
0$
1'
0(
#1720000000
1!
0"
0#
1$
1%
0&
0'
1(
#1730000000
1#
0$
1'
0(
#1740000000
1"
0#
1&
0'
#1750000000
1#
1$
1'
1(
#1760000000
0!
0"
0#
0$
0%
0&
0'
0(
#1770000000
1#
1'
#1780000000
1"
0#
1$
1&
0'
1(
#1790000000
1#
0$
1'
0(
#1800000000
1!
0"
0#
1$
1%
0&
0'
1(
#1810000000
1#
0$
1'
0(
#1820000000
1"
0#
1&
0'
#1830000000
1#
1$
1'
1(
#1840000000
0!
0"
0#
0$
0%
0&
0'
0(
#1850000000
1#
1'
#1860000000
1"
0#
1$
1&
0'
1(
#1870000000
1#
0$
1'
0(
#1880000000
1!
0"
0#
1$
1%
0&
0'
1(
#1890000000
1#
0$
1'
0(
#1900000000
1"
0#
1&
0'
#1910000000
1#
1$
1'
1(
#1920000000
0!
0"
0#
0$
0%
0&
0'
0(
#1930000000
1#
1'
#1940000000
1"
0#
1$
1&
0'
1(
#1950000000
1#
0$
1'
0(
#1960000000
1!
0"
0#
1$
1%
0&
0'
1(
#1970000000
1#
0$
1'
0(
#1980000000
1"
0#
1&
0'
#1990000000
1#
1$
1'
1(
#2000000000
0!
0"
0#
0$
0%
0&
0'
0(
#2010000000
1#
1'
#2020000000
1"
0#
1$
1&
0'
1(
#2030000000
1#
0$
1'
0(
#2040000000
1!
0"
0#
1$
1%
0&
0'
1(
#2050000000
1#
0$
1'
0(
#2060000000
1"
0#
1&
0'
#2070000000
1#
1$
1'
1(
#2080000000
0!
0"
0#
0$
0%
0&
0'
0(
#2090000000
1#
1'
#2100000000
1"
0#
1$
1&
0'
1(
#2110000000
1#
0$
1'
0(
#2120000000
1!
0"
0#
1$
1%
0&
0'
1(
#2130000000
1#
0$
1'
0(
#2140000000
1"
0#
1&
0'
#2150000000
1#
1$
1'
1(
#2160000000
0!
0"
0#
0$
0%
0&
0'
0(
#2170000000
1#
1'
#2180000000
1"
0#
1$
1&
0'
1(
#2190000000
1#
0$
1'
0(
#2200000000
1!
0"
0#
1$
1%
0&
0'
1(
#2210000000
1#
0$
1'
0(
#2220000000
1"
0#
1&
0'
#2230000000
1#
1$
1'
1(
#2240000000
0!
0"
0#
0$
0%
0&
0'
0(
#2250000000
1#
1'
#2260000000
1"
0#
1$
1&
0'
1(
#2270000000
1#
0$
1'
0(
#2280000000
1!
0"
0#
1$
1%
0&
0'
1(
#2290000000
1#
0$
1'
0(
#2300000000
1"
0#
1&
0'
#2310000000
1#
1$
1'
1(
#2320000000
0!
0"
0#
0$
0%
0&
0'
0(
#2330000000
1#
1'
#2340000000
1"
0#
1$
1&
0'
1(
#2350000000
1#
0$
1'
0(
#2360000000
1!
0"
0#
1$
1%
0&
0'
1(
#2370000000
1#
0$
1'
0(
#2380000000
1"
0#
1&
0'
#2390000000
1#
1$
1'
1(
#2400000000
0!
0"
0#
0$
0%
0&
0'
0(
#2410000000
1#
1'
#2420000000
1"
0#
1$
1&
0'
1(
#2430000000
1#
0$
1'
0(
#2440000000
1!
0"
0#
1$
1%
0&
0'
1(
#2450000000
1#
0$
1'
0(
#2460000000
1"
0#
1&
0'
#2470000000
1#
1$
1'
1(
#2480000000
0!
0"
0#
0$
0%
0&
0'
0(
#2490000000
1#
1'
#2500000000
1"
0#
1$
1&
0'
1(
#2510000000
1#
0$
1'
0(
#2520000000
1!
0"
0#
1$
1%
0&
0'
1(
#2530000000
1#
0$
1'
0(
#2540000000
1"
0#
1&
0'
#2550000000
1#
1$
1'
1(
#2560000000
0!
0"
0#
0$
0%
0&
0'
0(
#2570000000
1#
1'
#2580000000
1"
0#
1$
1&
0'
1(
#2590000000
1#
0$
1'
0(
#2600000000
1!
0"
0#
1$
1%
0&
0'
1(
#2610000000
1#
0$
1'
0(
#2620000000
1"
0#
1&
0'
#2630000000
1#
1$
1'
1(
#2640000000
0!
0"
0#
0$
0%
0&
0'
0(
#2650000000
1#
1'
#2660000000
1"
0#
1$
1&
0'
1(
#2670000000
1#
0$
1'
0(
#2680000000
1!
0"
0#
1$
1%
0&
0'
1(
#2690000000
1#
0$
1'
0(
#2700000000
1"
0#
1&
0'
#2710000000
1#
1$
1'
1(
#2720000000
0!
0"
0#
0$
0%
0&
0'
0(
#2730000000
1#
1'
#2740000000
1"
0#
1$
1&
0'
1(
#2750000000
1#
0$
1'
0(
#2760000000
1!
0"
0#
1$
1%
0&
0'
1(
#2770000000
1#
0$
1'
0(
#2780000000
1"
0#
1&
0'
#2790000000
1#
1$
1'
1(
#2800000000
0!
0"
0#
0$
0%
0&
0'
0(
#2810000000
1#
1'
#2820000000
1"
0#
1$
1&
0'
1(
#2830000000
1#
0$
1'
0(
#2840000000
1!
0"
0#
1$
1%
0&
0'
1(
#2850000000
1#
0$
1'
0(
#2860000000
1"
0#
1&
0'
#2870000000
1#
1$
1'
1(
#2880000000
0!
0"
0#
0$
0%
0&
0'
0(
#2890000000
1#
1'
#2900000000
1"
0#
1$
1&
0'
1(
#2910000000
1#
0$
1'
0(
#2920000000
1!
0"
0#
1$
1%
0&
0'
1(
#2930000000
1#
0$
1'
0(
#2940000000
1"
0#
1&
0'
#2950000000
1#
1$
1'
1(
#2960000000
0!
0"
0#
0$
0%
0&
0'
0(
#2970000000
1#
1'
#2980000000
1"
0#
1$
1&
0'
1(
#2990000000
1#
0$
1'
0(
#3000000000
1!
0"
0#
1$
1%
0&
0'
1(
#3010000000
1#
0$
1'
0(
#3020000000
1"
0#
1&
0'
#3030000000
1#
1$
1'
1(
#3040000000
0!
0"
0#
0$
0%
0&
0'
0(
#3050000000
1#
1'
#3060000000
1"
0#
1$
1&
0'
1(
#3070000000
1#
0$
1'
0(
#3080000000
1!
0"
0#
1$
1%
0&
0'
1(
#3090000000
1#
0$
1'
0(
#3100000000
1"
0#
1&
0'
#3110000000
1#
1$
1'
1(
#3120000000
0!
0"
0#
0$
0%
0&
0'
0(
#3130000000
1#
1'
#3140000000
1"
0#
1$
1&
0'
1(
#3150000000
1#
0$
1'
0(
#3160000000
1!
0"
0#
1$
1%
0&
0'
1(
#3170000000
1#
0$
1'
0(
#3180000000
1"
0#
1&
0'
#3190000000
1#
1$
1'
1(
#3200000000
0!
0"
0#
0$
0%
0&
0'
0(
#3210000000
1#
1'
#3220000000
1"
0#
1$
1&
0'
1(
#3230000000
1#
0$
1'
0(
#3240000000
1!
0"
0#
1$
1%
0&
0'
1(
#3250000000
1#
0$
1'
0(
#3260000000
1"
0#
1&
0'
#3270000000
1#
1$
1'
1(
#3280000000
0!
0"
0#
0$
0%
0&
0'
0(
#3290000000
1#
1'
#3300000000
1"
0#
1$
1&
0'
1(
#3310000000
1#
0$
1'
0(
#3320000000
1!
0"
0#
1$
1%
0&
0'
1(
#3330000000
1#
0$
1'
0(
#3340000000
1"
0#
1&
0'
#3350000000
1#
1$
1'
1(
#3360000000
0!
0"
0#
0$
0%
0&
0'
0(
#3370000000
1#
1'
#3380000000
1"
0#
1$
1&
0'
1(
#3390000000
1#
0$
1'
0(
#3400000000
1!
0"
0#
1$
1%
0&
0'
1(
#3410000000
1#
0$
1'
0(
#3420000000
1"
0#
1&
0'
#3430000000
1#
1$
1'
1(
#3440000000
0!
0"
0#
0$
0%
0&
0'
0(
#3450000000
1#
1'
#3460000000
1"
0#
1$
1&
0'
1(
#3470000000
1#
0$
1'
0(
#3480000000
1!
0"
0#
1$
1%
0&
0'
1(
#3490000000
1#
0$
1'
0(
#3500000000
1"
0#
1&
0'
#3510000000
1#
1$
1'
1(
#3520000000
0!
0"
0#
0$
0%
0&
0'
0(
#3530000000
1#
1'
#3540000000
1"
0#
1$
1&
0'
1(
#3550000000
1#
0$
1'
0(
#3560000000
1!
0"
0#
1$
1%
0&
0'
1(
#3570000000
1#
0$
1'
0(
#3580000000
1"
0#
1&
0'
#3590000000
1#
1$
1'
1(
#3600000000
0!
0"
0#
0$
0%
0&
0'
0(
#3610000000
1#
1'
#3620000000
1"
0#
1$
1&
0'
1(
#3630000000
1#
0$
1'
0(
#3640000000
1!
0"
0#
1$
1%
0&
0'
1(
#3650000000
1#
0$
1'
0(
#3660000000
1"
0#
1&
0'
#3670000000
1#
1$
1'
1(
#3680000000
0!
0"
0#
0$
0%
0&
0'
0(
#3690000000
1#
1'
#3700000000
1"
0#
1$
1&
0'
1(
#3710000000
1#
0$
1'
0(
#3720000000
1!
0"
0#
1$
1%
0&
0'
1(
#3730000000
1#
0$
1'
0(
#3740000000
1"
0#
1&
0'
#3750000000
1#
1$
1'
1(
#3760000000
0!
0"
0#
0$
0%
0&
0'
0(
#3770000000
1#
1'
#3780000000
1"
0#
1$
1&
0'
1(
#3790000000
1#
0$
1'
0(
#3800000000
1!
0"
0#
1$
1%
0&
0'
1(
#3810000000
1#
0$
1'
0(
#3820000000
1"
0#
1&
0'
#3830000000
1#
1$
1'
1(
#3840000000
0!
0"
0#
0$
0%
0&
0'
0(
#3850000000
1#
1'
#3860000000
1"
0#
1$
1&
0'
1(
#3870000000
1#
0$
1'
0(
#3880000000
1!
0"
0#
1$
1%
0&
0'
1(
#3890000000
1#
0$
1'
0(
#3900000000
1"
0#
1&
0'
#3910000000
1#
1$
1'
1(
#3920000000
0!
0"
0#
0$
0%
0&
0'
0(
#3930000000
1#
1'
#3940000000
1"
0#
1$
1&
0'
1(
#3950000000
1#
0$
1'
0(
#3960000000
1!
0"
0#
1$
1%
0&
0'
1(
#3970000000
1#
0$
1'
0(
#3980000000
1"
0#
1&
0'
#3990000000
1#
1$
1'
1(
#4000000000
0!
0"
0#
0$
0%
0&
0'
0(
#4010000000
1#
1'
#4020000000
1"
0#
1$
1&
0'
1(
#4030000000
1#
0$
1'
0(
#4040000000
1!
0"
0#
1$
1%
0&
0'
1(
#4050000000
1#
0$
1'
0(
#4060000000
1"
0#
1&
0'
#4070000000
1#
1$
1'
1(
#4080000000
0!
0"
0#
0$
0%
0&
0'
0(
#4090000000
1#
1'
#4100000000
1"
0#
1$
1&
0'
1(
#4110000000
1#
0$
1'
0(
#4120000000
1!
0"
0#
1$
1%
0&
0'
1(
#4130000000
1#
0$
1'
0(
#4140000000
1"
0#
1&
0'
#4150000000
1#
1$
1'
1(
#4160000000
0!
0"
0#
0$
0%
0&
0'
0(
#4170000000
1#
1'
#4180000000
1"
0#
1$
1&
0'
1(
#4190000000
1#
0$
1'
0(
#4200000000
1!
0"
0#
1$
1%
0&
0'
1(
#4210000000
1#
0$
1'
0(
#4220000000
1"
0#
1&
0'
#4230000000
1#
1$
1'
1(
#4240000000
0!
0"
0#
0$
0%
0&
0'
0(
#4250000000
1#
1'
#4260000000
1"
0#
1$
1&
0'
1(
#4270000000
1#
0$
1'
0(
#4280000000
1!
0"
0#
1$
1%
0&
0'
1(
#4290000000
1#
0$
1'
0(
#4300000000
1"
0#
1&
0'
#4310000000
1#
1$
1'
1(
#4320000000
0!
0"
0#
0$
0%
0&
0'
0(
#4330000000
1#
1'
#4340000000
1"
0#
1$
1&
0'
1(
#4350000000
1#
0$
1'
0(
#4360000000
1!
0"
0#
1$
1%
0&
0'
1(
#4370000000
1#
0$
1'
0(
#4380000000
1"
0#
1&
0'
#4390000000
1#
1$
1'
1(
#4400000000
0!
0"
0#
0$
0%
0&
0'
0(
#4410000000
1#
1'
#4420000000
1"
0#
1$
1&
0'
1(
#4430000000
1#
0$
1'
0(
#4440000000
1!
0"
0#
1$
1%
0&
0'
1(
#4450000000
1#
0$
1'
0(
#4460000000
1"
0#
1&
0'
#4470000000
1#
1$
1'
1(
#4480000000
0!
0"
0#
0$
0%
0&
0'
0(
#4490000000
1#
1'
#4500000000
1"
0#
1$
1&
0'
1(
#4510000000
1#
0$
1'
0(
#4520000000
1!
0"
0#
1$
1%
0&
0'
1(
#4530000000
1#
0$
1'
0(
#4540000000
1"
0#
1&
0'
#4550000000
1#
1$
1'
1(
#4560000000
0!
0"
0#
0$
0%
0&
0'
0(
#4570000000
1#
1'
#4580000000
1"
0#
1$
1&
0'
1(
#4590000000
1#
0$
1'
0(
#4600000000
1!
0"
0#
1$
1%
0&
0'
1(
#4610000000
1#
0$
1'
0(
#4620000000
1"
0#
1&
0'
#4630000000
1#
1$
1'
1(
#4640000000
0!
0"
0#
0$
0%
0&
0'
0(
#4650000000
1#
1'
#4660000000
1"
0#
1$
1&
0'
1(
#4670000000
1#
0$
1'
0(
#4680000000
1!
0"
0#
1$
1%
0&
0'
1(
#4690000000
1#
0$
1'
0(
#4700000000
1"
0#
1&
0'
#4710000000
1#
1$
1'
1(
#4720000000
0!
0"
0#
0$
0%
0&
0'
0(
#4730000000
1#
1'
#4740000000
1"
0#
1$
1&
0'
1(
#4750000000
1#
0$
1'
0(
#4760000000
1!
0"
0#
1$
1%
0&
0'
1(
#4770000000
1#
0$
1'
0(
#4780000000
1"
0#
1&
0'
#4790000000
1#
1$
1'
1(
#4800000000
0!
0"
0#
0$
0%
0&
0'
0(
#4810000000
1#
1'
#4820000000
1"
0#
1$
1&
0'
1(
#4830000000
1#
0$
1'
0(
#4840000000
1!
0"
0#
1$
1%
0&
0'
1(
#4850000000
1#
0$
1'
0(
#4860000000
1"
0#
1&
0'
#4870000000
1#
1$
1'
1(
#4880000000
0!
0"
0#
0$
0%
0&
0'
0(
#4890000000
1#
1'
#4900000000
1"
0#
1$
1&
0'
1(
#4910000000
1#
0$
1'
0(
#4920000000
1!
0"
0#
1$
1%
0&
0'
1(
#4930000000
1#
0$
1'
0(
#4940000000
1"
0#
1&
0'
#4950000000
1#
1$
1'
1(
#4960000000
0!
0"
0#
0$
0%
0&
0'
0(
#4970000000
1#
1'
#4980000000
1"
0#
1$
1&
0'
1(
#4990000000
1#
0$
1'
0(
#5000000000
1!
0"
0#
1$
1%
0&
0'
1(
#5010000000
1#
0$
1'
0(
#5020000000
1"
0#
1&
0'
#5030000000
1#
1$
1'
1(
#5040000000
0!
0"
0#
0$
0%
0&
0'
0(
#5050000000
1#
1'
#5060000000
1"
0#
1$
1&
0'
1(
#5070000000
1#
0$
1'
0(
#5080000000
1!
0"
0#
1$
1%
0&
0'
1(
#5090000000
1#
0$
1'
0(
#5100000000
1"
0#
1&
0'
#5110000000
1#
1$
1'
1(
#5120000000
0!
0"
0#
0$
0%
0&
0'
0(
#5130000000
1#
1'
#5140000000
1"
0#
1$
1&
0'
1(
#5150000000
1#
0$
1'
0(
#5160000000
1!
0"
0#
1$
1%
0&
0'
1(
#5170000000
1#
0$
1'
0(
#5180000000
1"
0#
1&
0'
#5190000000
1#
1$
1'
1(
#5200000000
0!
0"
0#
0$
0%
0&
0'
0(
#5210000000
1#
1'
#5220000000
1"
0#
1$
1&
0'
1(
#5230000000
1#
0$
1'
0(
#5240000000
1!
0"
0#
1$
1%
0&
0'
1(
#5250000000
1#
0$
1'
0(
#5260000000
1"
0#
1&
0'
#5270000000
1#
1$
1'
1(
#5280000000
0!
0"
0#
0$
0%
0&
0'
0(
#5290000000
1#
1'
#5300000000
1"
0#
1$
1&
0'
1(
#5310000000
1#
0$
1'
0(
#5320000000
1!
0"
0#
1$
1%
0&
0'
1(
#5330000000
1#
0$
1'
0(
#5340000000
1"
0#
1&
0'
#5350000000
1#
1$
1'
1(
#5360000000
0!
0"
0#
0$
0%
0&
0'
0(
#5370000000
1#
1'
#5380000000
1"
0#
1$
1&
0'
1(
#5390000000
1#
0$
1'
0(
#5400000000
1!
0"
0#
1$
1%
0&
0'
1(
#5410000000
1#
0$
1'
0(
#5420000000
1"
0#
1&
0'
#5430000000
1#
1$
1'
1(
#5440000000
0!
0"
0#
0$
0%
0&
0'
0(
#5450000000
1#
1'
#5460000000
1"
0#
1$
1&
0'
1(
#5470000000
1#
0$
1'
0(
#5480000000
1!
0"
0#
1$
1%
0&
0'
1(
#5490000000
1#
0$
1'
0(
#5500000000
1"
0#
1&
0'
#5510000000
1#
1$
1'
1(
#5520000000
0!
0"
0#
0$
0%
0&
0'
0(
#5530000000
1#
1'
#5540000000
1"
0#
1$
1&
0'
1(
#5550000000
1#
0$
1'
0(
#5560000000
1!
0"
0#
1$
1%
0&
0'
1(
#5570000000
1#
0$
1'
0(
#5580000000
1"
0#
1&
0'
#5590000000
1#
1$
1'
1(
#5600000000
0!
0"
0#
0$
0%
0&
0'
0(
#5610000000
1#
1'
#5620000000
1"
0#
1$
1&
0'
1(
#5630000000
1#
0$
1'
0(
#5640000000
1!
0"
0#
1$
1%
0&
0'
1(
#5650000000
1#
0$
1'
0(
#5660000000
1"
0#
1&
0'
#5670000000
1#
1$
1'
1(
#5680000000
0!
0"
0#
0$
0%
0&
0'
0(
#5690000000
1#
1'
#5700000000
1"
0#
1$
1&
0'
1(
#5710000000
1#
0$
1'
0(
#5720000000
1!
0"
0#
1$
1%
0&
0'
1(
#5730000000
1#
0$
1'
0(
#5740000000
1"
0#
1&
0'
#5750000000
1#
1$
1'
1(
#5760000000
0!
0"
0#
0$
0%
0&
0'
0(
#5770000000
1#
1'
#5780000000
1"
0#
1$
1&
0'
1(
#5790000000
1#
0$
1'
0(
#5800000000
1!
0"
0#
1$
1%
0&
0'
1(
#5810000000
1#
0$
1'
0(
#5820000000
1"
0#
1&
0'
#5830000000
1#
1$
1'
1(
#5840000000
0!
0"
0#
0$
0%
0&
0'
0(
#5850000000
1#
1'
#5860000000
1"
0#
1$
1&
0'
1(
#5870000000
1#
0$
1'
0(
#5880000000
1!
0"
0#
1$
1%
0&
0'
1(
#5890000000
1#
0$
1'
0(
#5900000000
1"
0#
1&
0'
#5910000000
1#
1$
1'
1(
#5920000000
0!
0"
0#
0$
0%
0&
0'
0(
#5930000000
1#
1'
#5940000000
1"
0#
1$
1&
0'
1(
#5950000000
1#
0$
1'
0(
#5960000000
1!
0"
0#
1$
1%
0&
0'
1(
#5970000000
1#
0$
1'
0(
#5980000000
1"
0#
1&
0'
#5990000000
1#
1$
1'
1(
#6000000000
0!
0"
0#
0$
0%
0&
0'
0(
#6010000000
1#
1'
#6020000000
1"
0#
1$
1&
0'
1(
#6030000000
1#
0$
1'
0(
#6040000000
1!
0"
0#
1$
1%
0&
0'
1(
#6050000000
1#
0$
1'
0(
#6060000000
1"
0#
1&
0'
#6070000000
1#
1$
1'
1(
#6080000000
0!
0"
0#
0$
0%
0&
0'
0(
#6090000000
1#
1'
#6100000000
1"
0#
1$
1&
0'
1(
#6110000000
1#
0$
1'
0(
#6120000000
1!
0"
0#
1$
1%
0&
0'
1(
#6130000000
1#
0$
1'
0(
#6140000000
1"
0#
1&
0'
#6150000000
1#
1$
1'
1(
#6160000000
0!
0"
0#
0$
0%
0&
0'
0(
#6170000000
1#
1'
#6180000000
1"
0#
1$
1&
0'
1(
#6190000000
1#
0$
1'
0(
#6200000000
1!
0"
0#
1$
1%
0&
0'
1(
#6210000000
1#
0$
1'
0(
#6220000000
1"
0#
1&
0'
#6230000000
1#
1$
1'
1(
#6240000000
0!
0"
0#
0$
0%
0&
0'
0(
#6250000000
1#
1'
#6260000000
1"
0#
1$
1&
0'
1(
#6270000000
1#
0$
1'
0(
#6280000000
1!
0"
0#
1$
1%
0&
0'
1(
#6290000000
1#
0$
1'
0(
#6300000000
1"
0#
1&
0'
#6310000000
1#
1$
1'
1(
#6320000000
0!
0"
0#
0$
0%
0&
0'
0(
#6330000000
1#
1'
#6340000000
1"
0#
1$
1&
0'
1(
#6350000000
1#
0$
1'
0(
#6360000000
1!
0"
0#
1$
1%
0&
0'
1(
#6370000000
1#
0$
1'
0(
#6380000000
1"
0#
1&
0'
#6390000000
1#
1$
1'
1(
#6400000000
0!
0"
0#
0$
0%
0&
0'
0(
#6410000000
1#
1'
#6420000000
1"
0#
1$
1&
0'
1(
#6430000000
1#
0$
1'
0(
#6440000000
1!
0"
0#
1$
1%
0&
0'
1(
#6450000000
1#
0$
1'
0(
#6460000000
1"
0#
1&
0'
#6470000000
1#
1$
1'
1(
#6480000000
0!
0"
0#
0$
0%
0&
0'
0(
#6490000000
1#
1'
#6500000000
1"
0#
1$
1&
0'
1(
#6510000000
1#
0$
1'
0(
#6520000000
1!
0"
0#
1$
1%
0&
0'
1(
#6530000000
1#
0$
1'
0(
#6540000000
1"
0#
1&
0'
#6550000000
1#
1$
1'
1(
#6560000000
0!
0"
0#
0$
0%
0&
0'
0(
#6570000000
1#
1'
#6580000000
1"
0#
1$
1&
0'
1(
#6590000000
1#
0$
1'
0(
#6600000000
1!
0"
0#
1$
1%
0&
0'
1(
#6610000000
1#
0$
1'
0(
#6620000000
1"
0#
1&
0'
#6630000000
1#
1$
1'
1(
#6640000000
0!
0"
0#
0$
0%
0&
0'
0(
#6650000000
1#
1'
#6660000000
1"
0#
1$
1&
0'
1(
#6670000000
1#
0$
1'
0(
#6680000000
1!
0"
0#
1$
1%
0&
0'
1(
#6690000000
1#
0$
1'
0(
#6700000000
1"
0#
1&
0'
