exercise/exercise.vhd
entity ProficientEx is
    port (
        X, Y, Z : in bit;
        F       : out bit
    );
end entity;

architecture sys of ProficientEx is
    begin
        F <= (((not X) and (not Y) and Z) or (X and (not Y) and Z) or (X and Y and Z));
end architecture;

exercise/exercise1_tb.vhd
entity ProficientEx_tb is
    --tesbed does not have ports
end entity;

architecture system of ProficientEx_tb is
    component ProficientEx is
        port (
            X, Y, Z : in bit;
            F       : out bit
        );
    end component;

    --  Specifies which entity is bound with the component.
    for prac_0: ProficientEx use entity work.ProficientEx;
    signal X, Y, Z, F : bit;
    begin
    --  Component instantiation.
    prac_0: ProficientEx port map (X => X, Y => X, Z => X,
                            F => F);

    --  This process does the real job.
    process
    type pattern_type is record
        --  The inputs of the adder.
        X, Y, Z : bit;
        --  The expected outputs of the adder.
        F : bit;
    end record;
    --  The patterns to apply.
    type pattern_array is array (natural range <>) of pattern_type;
    constant patterns : pattern_array :=
        (('0', '0', '0', '0'),
        ('0', '0', '1', '1'),
        ('0', '1', '0', '0'),
        ('0', '1', '1', '0'),
        ('1', '0', '0', '0'),
        ('1', '0', '1', '1'),
        ('1', '1', '0', '0'),
        ('1', '1', '1', '1'));
    begin
    --  Check each pattern.
    for i in patterns'range loop
        --  Set the inputs.
        X <= patterns(i).X;
        Y <= patterns(i).Y;
        Z <= patterns(i).Z;
        --  Wait for the results.
        wait for 1 ns;
        --  Check the outputs.
        assert F = patterns(i).F
            report "bad sum value" severity error;
    end loop;
    assert false report "end of test" severity note;
    --  Wait forever; this will finish the simulation.
    wait;
    end process;

end architecture;

exercise/exercise.vcd
$date
  Tue Mar 22 00:45:05 2022
$end
$version
  GHDL v0
$end
$timescale
  1 fs
$end
$scope module standard $end
$upscope $end
$scope module proficientex_tb $end
$var reg 1 ! x $end
$var reg 1 " y $end
$var reg 1 # z $end
$var reg 1 $ f $end
$scope module prac_0 $end
$var reg 1 % x $end
$var reg 1 & y $end
$var reg 1 ' z $end
$var reg 1 ( f $end
$upscope $end
$upscope $end
$enddefinitions $end
#0
0!
0"
0#
0$
0%
0&
0'
0(
#1000000
1#
#2000000
1"
0#
#3000000
1#
#4000000
1!
0"
0#
1$
1%
1&
1'
1(
#5000000
1#
#6000000
1"
0#
#7000000
1#
